{
  "generated_at": "2026-03-11T15:04:01Z",
  "macro": [
    {
      "series": "M2SL",
      "latest_date": "2026-01-01",
      "latest_value": "22442.1"
    },
    {
      "series": "DGS10",
      "latest_date": "2026-03-09",
      "latest_value": "4.12"
    },
    {
      "series": "DGS2",
      "latest_date": "2026-03-09",
      "latest_value": "3.56"
    },
    {
      "series": "DTWEXBGS",
      "latest_date": "2026-03-06",
      "latest_value": "119.4910"
    },
    {
      "series": "VIXCLS",
      "latest_date": "2026-03-10",
      "latest_value": "24.93"
    }
  ],
  "market": [
    {
      "ticker": "QQQ",
      "ok": true,
      "currency": "USD",
      "exchange": "NGM",
      "regularMarketPrice": 608.979,
      "previousClose": null,
      "lastCloseSeries": 608.9786987304688,
      "chg_5d_pct": -0.29,
      "chg_20d_pct": -0.41,
      "ema20": 608.286,
      "ema50": 611.204,
      "sma200": 590.206,
      "overextension_200d_pct": 3.18,
      "rsi14": 49.76,
      "bb_upper": 615.343,
      "bb_lower": 597.769,
      "rel_volume": 0.28,
      "breakout_20": false,
      "intraday_15m_bias": "neutro",
      "score_tech": 54,
      "score": 46,
      "reasons": [
        "universo_prioritario",
        "price_above_ema20",
        "ema20_below_ema50",
        "macro_vix_alto"
      ],
      "score_social": 40.0,
      "earnings_label": "No Data",
      "score_macro_adj": -8,
      "score_asymmetry": 0,
      "fundamental_inflection_score": 0,
      "catalyst_score": 0,
      "spinoff_score": 0,
      "insider_score": 0,
      "options_flow_score": 0,
      "options_cp_ratio": null,
      "insider_buys": 0,
      "convergence_count": 0,
      "state": "WATCH",
      "score_final": 46,
      "confidence_pct": 46,
      "bubble_level": "Bajo",
      "argumento_en_contra": "Sin objeción crítica detectada",
      "decision_final": "AVOID"
    },
    {
      "ticker": "SPY",
      "ok": true,
      "currency": "USD",
      "exchange": "PCX",
      "regularMarketPrice": 677.08,
      "previousClose": null,
      "lastCloseSeries": 677.0800170898438,
      "chg_5d_pct": -1.17,
      "chg_20d_pct": -2.17,
      "ema20": 682.962,
      "ema50": 684.246,
      "sma200": 657.809,
      "overextension_200d_pct": 2.93,
      "rsi14": 43.33,
      "bb_upper": 694.009,
      "bb_lower": 673.418,
      "rel_volume": 0.23,
      "breakout_20": false,
      "intraday_15m_bias": "bajista",
      "score_tech": 33,
      "score": 17,
      "reasons": [
        "price_below_ema20",
        "ema20_below_ema50",
        "intraday_15m_bajista",
        "macro_vix_alto",
        "social_bearish"
      ],
      "score_social": -50.0,
      "earnings_label": "No Data",
      "score_macro_adj": -8,
      "score_asymmetry": 0,
      "fundamental_inflection_score": 0,
      "catalyst_score": 0,
      "spinoff_score": 0,
      "insider_score": 0,
      "options_flow_score": 0,
      "options_cp_ratio": null,
      "insider_buys": 0,
      "convergence_count": 0,
      "state": "WATCH",
      "score_final": 17,
      "confidence_pct": 17,
      "bubble_level": "Bajo",
      "argumento_en_contra": "Sin objeción crítica detectada",
      "decision_final": "AVOID"
    },
    {
      "ticker": "IWM",
      "ok": true,
      "currency": "USD",
      "exchange": "PCX",
      "regularMarketPrice": 253.42,
      "previousClose": null,
      "lastCloseSeries": 253.4199981689453,
      "chg_5d_pct": -3.19,
      "chg_20d_pct": -4.79,
      "ema20": 259.039,
      "ema50": 258.554,
      "sma200": 239.784,
      "overextension_200d_pct": 5.69,
      "rsi14": 40.69,
      "bb_upper": 269.599,
      "bb_lower": 251.636,
      "rel_volume": 0.45,
      "breakout_20": false,
      "intraday_15m_bias": "neutro",
      "score_tech": 40,
      "score": 32,
      "reasons": [
        "momento_5d_debil",
        "price_below_ema20",
        "ema20_above_ema50",
        "macro_vix_alto"
      ],
      "score_social": null,
      "earnings_label": "No Data",
      "score_macro_adj": -8,
      "score_asymmetry": 0,
      "fundamental_inflection_score": 0,
      "catalyst_score": 0,
      "spinoff_score": 0,
      "insider_score": 0,
      "options_flow_score": 0,
      "options_cp_ratio": null,
      "insider_buys": 0,
      "convergence_count": 0,
      "state": "WATCH",
      "score_final": 32,
      "confidence_pct": 32,
      "bubble_level": "Bajo",
      "argumento_en_contra": "Sin objeción crítica detectada",
      "decision_final": "AVOID"
    },
    {
      "ticker": "GLD",
      "ok": true,
      "currency": "USD",
      "exchange": "PCX",
      "regularMarketPrice": 475.93,
      "previousClose": null,
      "lastCloseSeries": 475.92999267578125,
      "chg_5d_pct": 0.88,
      "chg_20d_pct": 2.93,
      "ema20": 469.566,
      "ema50": 450.76,
      "sma200": 369.215,
      "overextension_200d_pct": 28.9,
      "rsi14": 55.3,
      "bb_upper": 490.494,
      "bb_lower": 449.78,
      "rel_volume": 0.22,
      "breakout_20": false,
      "intraday_15m_bias": "bajista",
      "score_tech": 76,
      "score": 50,
      "reasons": [
        "momento_5d_positivo",
        "tendencia_20d_positiva",
        "price_above_ema20",
        "ema20_above_ema50",
        "rsi_constructivo",
        "intraday_15m_bajista",
        "macro_vix_alto",
        "bubble_critical",
        "devil_advocate_active"
      ],
      "score_social": null,
      "earnings_label": "No Data",
      "score_macro_adj": -8,
      "score_asymmetry": 0,
      "fundamental_inflection_score": 0,
      "catalyst_score": 0,
      "spinoff_score": 0,
      "insider_score": 0,
      "options_flow_score": 0,
      "options_cp_ratio": null,
      "insider_buys": 0,
      "convergence_count": 1,
      "state": "WATCH",
      "score_final": 50,
      "confidence_pct": 50,
      "bubble_level": "Crítico",
      "argumento_en_contra": "Divergencia bajista: precio sube con volumen débil",
      "decision_final": "AVOID"
    },
    {
      "ticker": "TLT",
      "ok": true,
      "currency": "USD",
      "exchange": "NGM",
      "regularMarketPrice": 87.42,
      "previousClose": null,
      "lastCloseSeries": 87.41999816894531,
      "chg_5d_pct": -1.94,
      "chg_20d_pct": -1.25,
      "ema20": 88.882,
      "ema50": 88.645,
      "sma200": 88.141,
      "overextension_200d_pct": -0.82,
      "rsi14": 38.99,
      "bb_upper": 90.875,
      "bb_lower": 87.77,
      "rel_volume": 0.4,
      "breakout_20": false,
      "intraday_15m_bias": "bajista",
      "score_tech": 41,
      "score": 33,
      "reasons": [
        "price_below_ema20",
        "ema20_above_ema50",
        "bollinger_breakdown",
        "intraday_15m_bajista",
        "macro_vix_alto"
      ],
      "score_social": null,
      "earnings_label": "No Data",
      "score_macro_adj": -8,
      "score_asymmetry": 0,
      "fundamental_inflection_score": 0,
      "catalyst_score": 0,
      "spinoff_score": 0,
      "insider_score": 0,
      "options_flow_score": 0,
      "options_cp_ratio": null,
      "insider_buys": 0,
      "convergence_count": 0,
      "state": "WATCH",
      "score_final": 33,
      "confidence_pct": 33,
      "bubble_level": "Bajo",
      "argumento_en_contra": "Sin objeción crítica detectada",
      "decision_final": "AVOID"
    },
    {
      "ticker": "XLF",
      "ok": true,
      "currency": "USD",
      "exchange": "PCX",
      "regularMarketPrice": 49.56,
      "previousClose": null,
      "lastCloseSeries": 49.560001373291016,
      "chg_5d_pct": -3.77,
      "chg_20d_pct": -7.45,
      "ema20": 51.424,
      "ema50": 52.476,
      "sma200": 52.836,
      "overextension_200d_pct": -6.2,
      "rsi14": 32.13,
      "bb_upper": 53.164,
      "bb_lower": 49.714,
      "rel_volume": 0.3,
      "breakout_20": false,
      "intraday_15m_bias": "bajista",
      "score_tech": 0,
      "score": 42,
      "reasons": [
        "momento_5d_debil",
        "tendencia_20d_debil",
        "price_below_ema20",
        "ema20_below_ema50",
        "rsi_debil",
        "bollinger_breakdown",
        "intraday_15m_bajista",
        "macro_vix_alto"
      ],
      "score_social": null,
      "earnings_label": "No Data",
      "score_macro_adj": -8,
      "score_asymmetry": 0,
      "fundamental_inflection_score": 0,
      "catalyst_score": 0,
      "spinoff_score": 0,
      "insider_score": 0,
      "options_flow_score": 0,
      "options_cp_ratio": null,
      "insider_buys": 0,
      "convergence_count": 0,
      "state": "WATCH",
      "score_final": 42,
      "confidence_pct": 42,
      "bubble_level": "Bajo",
      "argumento_en_contra": "Sin objeción crítica detectada",
      "decision_final": "AVOID"
    },
    {
      "ticker": "XLV",
      "ok": true,
      "currency": "USD",
      "exchange": "PCX",
      "regularMarketPrice": 152.93,
      "previousClose": null,
      "lastCloseSeries": 152.92999267578125,
      "chg_5d_pct": -2.62,
      "chg_20d_pct": -1.55,
      "ema20": 155.742,
      "ema50": 155.492,
      "sma200": 144.709,
      "overextension_200d_pct": 5.68,
      "rsi14": 40.13,
      "bb_upper": 160.544,
      "bb_lower": 152.473,
      "rel_volume": 0.31,
      "breakout_20": false,
      "intraday_15m_bias": "neutro",
      "score_tech": 40,
      "score": 32,
      "reasons": [
        "momento_5d_debil",
        "price_below_ema20",
        "ema20_above_ema50",
        "macro_vix_alto"
      ],
      "score_social": null,
      "earnings_label": "No Data",
      "score_macro_adj": -8,
      "score_asymmetry": 0,
      "fundamental_inflection_score": 0,
      "catalyst_score": 0,
      "spinoff_score": 0,
      "insider_score": 0,
      "options_flow_score": 0,
      "options_cp_ratio": null,
      "insider_buys": 0,
      "convergence_count": 0,
      "state": "WATCH",
      "score_final": 32,
      "confidence_pct": 32,
      "bubble_level": "Bajo",
      "argumento_en_contra": "Sin objeción crítica detectada",
      "decision_final": "AVOID"
    },
    {
      "ticker": "XLE",
      "ok": true,
      "currency": "USD",
      "exchange": "PCX",
      "regularMarketPrice": 56.695,
      "previousClose": null,
      "lastCloseSeries": 56.69499969482422,
      "chg_5d_pct": 0.9,
      "chg_20d_pct": 5.81,
      "ema20": 55.144,
      "ema50": 52.258,
      "sma200": 45.728,
      "overextension_200d_pct": 23.98,
      "rsi14": 66.04,
      "bb_upper": 57.32,
      "bb_lower": 53.62,
      "rel_volume": 0.32,
      "breakout_20": false,
      "intraday_15m_bias": "alcista",
      "score_tech": 96,
      "score": 70,
      "reasons": [
        "momento_5d_positivo",
        "tendencia_20d_fuerte",
        "price_above_ema20",
        "ema20_above_ema50",
        "rsi_constructivo",
        "intraday_15m_alcista",
        "macro_vix_alto",
        "bubble_critical",
        "devil_advocate_active"
      ],
      "score_social": null,
      "earnings_label": "No Data",
      "score_macro_adj": -8,
      "score_asymmetry": 0,
      "fundamental_inflection_score": 0,
      "catalyst_score": 0,
      "spinoff_score": 0,
      "insider_score": 0,
      "options_flow_score": 0,
      "options_cp_ratio": null,
      "insider_buys": 0,
      "convergence_count": 1,
      "state": "WATCH",
      "score_final": 70,
      "confidence_pct": 70,
      "bubble_level": "Crítico",
      "argumento_en_contra": "Divergencia bajista: precio sube con volumen débil",
      "decision_final": "HOLD"
    },
    {
      "ticker": "XLI",
      "ok": true,
      "currency": "USD",
      "exchange": "PCX",
      "regularMarketPrice": 169.905,
      "previousClose": null,
      "lastCloseSeries": 169.90499877929688,
      "chg_5d_pct": -3.45,
      "chg_20d_pct": -2.3,
      "ema20": 172.712,
      "ema50": 168.859,
      "sma200": 155.457,
      "overextension_200d_pct": 9.29,
      "rsi14": 44.34,
      "bb_upper": 179.729,
      "bb_lower": 169.258,
      "rel_volume": 0.38,
      "breakout_20": false,
      "intraday_15m_bias": "bajista",
      "score_tech": 35,
      "score": 27,
      "reasons": [
        "momento_5d_debil",
        "price_below_ema20",
        "ema20_above_ema50",
        "intraday_15m_bajista",
        "macro_vix_alto"
      ],
      "score_social": null,
      "earnings_label": "No Data",
      "score_macro_adj": -8,
      "score_asymmetry": 0,
      "fundamental_inflection_score": 0,
      "catalyst_score": 0,
      "spinoff_score": 0,
      "insider_score": 0,
      "options_flow_score": 0,
      "options_cp_ratio": null,
      "insider_buys": 0,
      "convergence_count": 0,
      "state": "WATCH",
      "score_final": 27,
      "confidence_pct": 27,
      "bubble_level": "Bajo",
      "argumento_en_contra": "Sin objeción crítica detectada",
      "decision_final": "AVOID"
    },
    {
      "ticker": "NVDA",
      "ok": true,
      "currency": "USD",
      "exchange": "NMS",
      "regularMarketPrice": 186.345,
      "previousClose": null,
      "lastCloseSeries": 186.34500122070312,
      "chg_5d_pct": 1.81,
      "chg_20d_pct": -1.16,
      "ema20": 184.603,
      "ema50": 184.997,
      "sma200": 176.909,
      "overextension_200d_pct": 5.33,
      "rsi14": 51.69,
      "bb_upper": 195.026,
      "bb_lower": 176.274,
      "rel_volume": 0.27,
      "breakout_20": false,
      "intraday_15m_bias": "alcista",
      "score_tech": 70,
      "score": 54,
      "reasons": [
        "momento_5d_positivo",
        "universo_prioritario",
        "price_above_ema20",
        "ema20_below_ema50",
        "rsi_constructivo",
        "intraday_15m_alcista",
        "macro_vix_alto",
        "devil_advocate_active"
      ],
      "score_social": -14.3,
      "earnings_label": "No Data",
      "score_macro_adj": -8,
      "score_asymmetry": 0,
      "fundamental_inflection_score": 0,
      "catalyst_score": 0,
      "spinoff_score": 0,
      "insider_score": 0,
      "options_flow_score": 0,
      "options_cp_ratio": null,
      "insider_buys": 0,
      "convergence_count": 1,
      "state": "WATCH",
      "score_final": 54,
      "confidence_pct": 54,
      "bubble_level": "Bajo",
      "argumento_en_contra": "Divergencia bajista: precio sube con volumen débil",
      "decision_final": "AVOID"
    },
    {
      "ticker": "MSFT",
      "ok": true,
      "currency": "USD",
      "exchange": "NMS",
      "regularMarketPrice": 403.78,
      "previousClose": null,
      "lastCloseSeries": 403.7799987792969,
      "chg_5d_pct": -0.35,
      "chg_20d_pct": -2.3,
      "ema20": 407.186,
      "ema50": 427.767,
      "sma200": 483.822,
      "overextension_200d_pct": -16.54,
      "rsi14": 44.0,
      "bb_upper": 413.584,
      "bb_lower": 387.864,
      "rel_volume": 0.24,
      "breakout_20": false,
      "intraday_15m_bias": "bajista",
      "score_tech": 37,
      "score": 37,
      "reasons": [
        "universo_prioritario",
        "price_below_ema20",
        "ema20_below_ema50",
        "intraday_15m_bajista",
        "macro_vix_alto",
        "social_bullish"
      ],
      "score_social": 100.0,
      "earnings_label": "No Data",
      "score_macro_adj": -8,
      "score_asymmetry": 0,
      "fundamental_inflection_score": 0,
      "catalyst_score": 0,
      "spinoff_score": 0,
      "insider_score": 0,
      "options_flow_score": 0,
      "options_cp_ratio": null,
      "insider_buys": 0,
      "convergence_count": 1,
      "state": "WATCH",
      "score_final": 37,
      "confidence_pct": 37,
      "bubble_level": "Bajo",
      "argumento_en_contra": "Sin objeción crítica detectada",
      "decision_final": "AVOID"
    },
    {
      "ticker": "AMZN",
      "ok": true,
      "currency": "USD",
      "exchange": "NMS",
      "regularMarketPrice": 213.36,
      "previousClose": null,
      "lastCloseSeries": 213.36000061035156,
      "chg_5d_pct": -1.6,
      "chg_20d_pct": 3.09,
      "ema20": 213.543,
      "ema50": 219.596,
      "sma200": 224.649,
      "overextension_200d_pct": -5.02,
      "rsi14": 47.67,
      "bb_upper": 219.392,
      "bb_lower": 197.912,
      "rel_volume": 0.18,
      "breakout_20": false,
      "intraday_15m_bias": "bajista",
      "score_tech": 45,
      "score": 37,
      "reasons": [
        "tendencia_20d_positiva",
        "universo_prioritario",
        "price_below_ema20",
        "ema20_below_ema50",
        "intraday_15m_bajista",
        "macro_vix_alto"
      ],
      "score_social": null,
      "earnings_label": "No Data",
      "score_macro_adj": -8,
      "score_asymmetry": 0,
      "fundamental_inflection_score": 0,
      "catalyst_score": 0,
      "spinoff_score": 0,
      "insider_score": 0,
      "options_flow_score": 0,
      "options_cp_ratio": null,
      "insider_buys": 0,
      "convergence_count": 0,
      "state": "WATCH",
      "score_final": 37,
      "confidence_pct": 37,
      "bubble_level": "Bajo",
      "argumento_en_contra": "Sin objeción crítica detectada",
      "decision_final": "AVOID"
    },
    {
      "ticker": "META",
      "ok": true,
      "currency": "USD",
      "exchange": "NMS",
      "regularMarketPrice": 651.455,
      "previousClose": null,
      "lastCloseSeries": 651.4550170898438,
      "chg_5d_pct": -2.44,
      "chg_20d_pct": -2.87,
      "ema20": 654.041,
      "ema50": 656.603,
      "sma200": 691.719,
      "overextension_200d_pct": -5.82,
      "rsi14": 48.52,
      "bb_upper": 668.044,
      "bb_lower": 633.092,
      "rel_volume": 0.21,
      "breakout_20": false,
      "intraday_15m_bias": "bajista",
      "score_tech": 27,
      "score": 24,
      "reasons": [
        "momento_5d_debil",
        "universo_prioritario",
        "price_below_ema20",
        "ema20_below_ema50",
        "intraday_15m_bajista",
        "macro_vix_alto",
        "catalyst_detected"
      ],
      "score_social": 11.1,
      "earnings_label": "No Data",
      "score_macro_adj": -8,
      "score_asymmetry": 5,
      "fundamental_inflection_score": 0,
      "catalyst_score": 5,
      "spinoff_score": 0,
      "insider_score": 0,
      "options_flow_score": 0,
      "options_cp_ratio": null,
      "insider_buys": 0,
      "convergence_count": 0,
      "state": "WATCH",
      "score_final": 24,
      "confidence_pct": 24,
      "bubble_level": "Bajo",
      "argumento_en_contra": "Sin objeción crítica detectada",
      "decision_final": "AVOID"
    },
    {
      "ticker": "AMD",
      "ok": true,
      "currency": "USD",
      "exchange": "NMS",
      "regularMarketPrice": 205.755,
      "previousClose": null,
      "lastCloseSeries": 205.7550048828125,
      "chg_5d_pct": 1.82,
      "chg_20d_pct": -3.66,
      "ema20": 204.934,
      "ema50": 211.883,
      "sma200": 189.991,
      "overextension_200d_pct": 8.3,
      "rsi14": 48.97,
      "bb_upper": 214.357,
      "bb_lower": 191.037,
      "rel_volume": 0.27,
      "breakout_20": false,
      "intraday_15m_bias": "neutro",
      "score_tech": 60,
      "score": 52,
      "reasons": [
        "momento_5d_positivo",
        "universo_prioritario",
        "price_above_ema20",
        "ema20_below_ema50",
        "macro_vix_alto",
        "social_bullish",
        "devil_advocate_active"
      ],
      "score_social": 70.0,
      "earnings_label": "No Data",
      "score_macro_adj": -8,
      "score_asymmetry": 0,
      "fundamental_inflection_score": 0,
      "catalyst_score": 0,
      "spinoff_score": 0,
      "insider_score": 0,
      "options_flow_score": 0,
      "options_cp_ratio": null,
      "insider_buys": 0,
      "convergence_count": 2,
      "state": "WATCH",
      "score_final": 52,
      "confidence_pct": 52,
      "bubble_level": "Bajo",
      "argumento_en_contra": "Divergencia bajista: precio sube con volumen débil",
      "decision_final": "AVOID"
    },
    {
      "ticker": "TSLA",
      "ok": true,
      "currency": "USD",
      "exchange": "NMS",
      "regularMarketPrice": 410.26,
      "previousClose": null,
      "lastCloseSeries": 410.260009765625,
      "chg_5d_pct": 1.06,
      "chg_20d_pct": -3.52,
      "ema20": 407.933,
      "ema50": 418.83,
      "sma200": 393.042,
      "overextension_200d_pct": 4.38,
      "rsi14": 49.48,
      "bb_upper": 424.556,
      "bb_lower": 391.255,
      "rel_volume": 0.48,
      "breakout_20": false,
      "intraday_15m_bias": "alcista",
      "score_tech": 61,
      "score": 45,
      "reasons": [
        "momento_5d_positivo",
        "price_above_ema20",
        "ema20_below_ema50",
        "intraday_15m_alcista",
        "macro_vix_alto",
        "devil_advocate_active"
      ],
      "score_social": 11.1,
      "earnings_label": "No Data",
      "score_macro_adj": -8,
      "score_asymmetry": 0,
      "fundamental_inflection_score": 0,
      "catalyst_score": 0,
      "spinoff_score": 0,
      "insider_score": 0,
      "options_flow_score": 0,
      "options_cp_ratio": null,
      "insider_buys": 0,
      "convergence_count": 1,
      "state": "WATCH",
      "score_final": 45,
      "confidence_pct": 45,
      "bubble_level": "Bajo",
      "argumento_en_contra": "Divergencia bajista: precio sube con volumen débil",
      "decision_final": "AVOID"
    },
    {
      "ticker": "AVGO",
      "ok": true,
      "currency": "USD",
      "exchange": "NMS",
      "regularMarketPrice": 342.96,
      "previousClose": null,
      "lastCloseSeries": 342.9599914550781,
      "chg_5d_pct": 8.01,
      "chg_20d_pct": 0.74,
      "ema20": 331.618,
      "ema50": 335.186,
      "sma200": 322.397,
      "overextension_200d_pct": 6.38,
      "rsi14": 57.4,
      "bb_upper": 347.932,
      "bb_lower": 312.659,
      "rel_volume": 0.21,
      "breakout_20": false,
      "intraday_15m_bias": "neutro",
      "score_tech": 79,
      "score": 57,
      "reasons": [
        "momento_5d_fuerte",
        "tendencia_20d_positiva",
        "universo_prioritario",
        "price_above_ema20",
        "ema20_below_ema50",
        "rsi_constructivo",
        "macro_vix_alto",
        "earnings_calendar_signal",
        "devil_advocate_active"
      ],
      "score_social": null,
      "earnings_label": "Earnings Miss/Inline",
      "score_macro_adj": -8,
      "score_asymmetry": 0,
      "fundamental_inflection_score": 0,
      "catalyst_score": 0,
      "spinoff_score": 0,
      "insider_score": 0,
      "options_flow_score": 0,
      "options_cp_ratio": null,
      "insider_buys": 0,
      "convergence_count": 1,
      "state": "WATCH",
      "score_final": 57,
      "confidence_pct": 57,
      "bubble_level": "Medio",
      "argumento_en_contra": "Divergencia bajista: precio sube con volumen débil",
      "decision_final": "AVOID"
    },
    {
      "ticker": "AAPL",
      "ok": true,
      "currency": "USD",
      "exchange": "NMS",
      "regularMarketPrice": 260.445,
      "previousClose": null,
      "lastCloseSeries": 260.44500732421875,
      "chg_5d_pct": -0.79,
      "chg_20d_pct": -4.84,
      "ema20": 263.605,
      "ema50": 264.576,
      "sma200": 245.03,
      "overextension_200d_pct": 6.29,
      "rsi14": 44.97,
      "bb_upper": 274.977,
      "bb_lower": 253.621,
      "rel_volume": 0.13,
      "breakout_20": false,
      "intraday_15m_bias": "bajista",
      "score_tech": 33,
      "score": 25,
      "reasons": [
        "price_below_ema20",
        "ema20_below_ema50",
        "intraday_15m_bajista",
        "macro_vix_alto"
      ],
      "score_social": null,
      "earnings_label": "No Data",
      "score_macro_adj": -8,
      "score_asymmetry": 0,
      "fundamental_inflection_score": 0,
      "catalyst_score": 0,
      "spinoff_score": 0,
      "insider_score": 0,
      "options_flow_score": 0,
      "options_cp_ratio": null,
      "insider_buys": 0,
      "convergence_count": 0,
      "state": "WATCH",
      "score_final": 25,
      "confidence_pct": 25,
      "bubble_level": "Bajo",
      "argumento_en_contra": "Sin objeción crítica detectada",
      "decision_final": "AVOID"
    },
    {
      "ticker": "GOOGL",
      "ok": true,
      "currency": "USD",
      "exchange": "NMS",
      "regularMarketPrice": 310.18,
      "previousClose": null,
      "lastCloseSeries": 310.18011474609375,
      "chg_5d_pct": 2.33,
      "chg_20d_pct": -2.64,
      "ema20": 309.468,
      "ema50": 311.87,
      "sma200": 255.156,
      "overextension_200d_pct": 21.56,
      "rsi14": 48.84,
      "bb_upper": 315.696,
      "bb_lower": 298.254,
      "rel_volume": 0.24,
      "breakout_20": false,
      "intraday_15m_bias": "alcista",
      "score_tech": 67,
      "score": 41,
      "reasons": [
        "momento_5d_fuerte",
        "price_above_ema20",
        "ema20_below_ema50",
        "intraday_15m_alcista",
        "macro_vix_alto",
        "bubble_critical",
        "devil_advocate_active"
      ],
      "score_social": null,
      "earnings_label": "No Data",
      "score_macro_adj": -8,
      "score_asymmetry": 0,
      "fundamental_inflection_score": 0,
      "catalyst_score": 0,
      "spinoff_score": 0,
      "insider_score": 0,
      "options_flow_score": 0,
      "options_cp_ratio": null,
      "insider_buys": 0,
      "convergence_count": 1,
      "state": "WATCH",
      "score_final": 41,
      "confidence_pct": 41,
      "bubble_level": "Crítico",
      "argumento_en_contra": "Divergencia bajista: precio sube con volumen débil",
      "decision_final": "AVOID"
    },
    {
      "ticker": "JPM",
      "ok": true,
      "currency": "USD",
      "exchange": "NYQ",
      "regularMarketPrice": 286.97,
      "previousClose": null,
      "lastCloseSeries": 286.9700012207031,
      "chg_5d_pct": -4.15,
      "chg_20d_pct": -9.84,
      "ema20": 298.734,
      "ema50": 305.033,
      "sma200": 300.524,
      "overextension_200d_pct": -4.51,
      "rsi14": 34.3,
      "bb_upper": 314.612,
      "bb_lower": 285.52,
      "rel_volume": 0.21,
      "breakout_20": false,
      "intraday_15m_bias": "bajista",
      "score_tech": 3,
      "score": 0,
      "reasons": [
        "momento_5d_debil",
        "tendencia_20d_debil",
        "price_below_ema20",
        "ema20_below_ema50",
        "rsi_debil",
        "intraday_15m_bajista",
        "macro_vix_alto",
        "social_bearish"
      ],
      "score_social": -81.8,
      "earnings_label": "No Data",
      "score_macro_adj": -8,
      "score_asymmetry": 0,
      "fundamental_inflection_score": 0,
      "catalyst_score": 0,
      "spinoff_score": 0,
      "insider_score": 0,
      "options_flow_score": 0,
      "options_cp_ratio": null,
      "insider_buys": 0,
      "convergence_count": 0,
      "state": "WATCH",
      "score_final": 0,
      "confidence_pct": 0,
      "bubble_level": "Bajo",
      "argumento_en_contra": "Sin objeción crítica detectada",
      "decision_final": "AVOID"
    },
    {
      "ticker": "UNH",
      "ok": true,
      "currency": "USD",
      "exchange": "NYQ",
      "regularMarketPrice": 282.745,
      "previousClose": null,
      "lastCloseSeries": 282.7449951171875,
      "chg_5d_pct": -3.16,
      "chg_20d_pct": 3.49,
      "ema20": 288.456,
      "ema50": 300.395,
      "sma200": 314.828,
      "overextension_200d_pct": -10.19,
      "rsi14": 42.55,
      "bb_upper": 296.899,
      "bb_lower": 276.673,
      "rel_volume": 0.19,
      "breakout_20": false,
      "intraday_15m_bias": "neutro",
      "score_tech": 36,
      "score": 28,
      "reasons": [
        "momento_5d_debil",
        "tendencia_20d_positiva",
        "price_below_ema20",
        "ema20_below_ema50",
        "macro_vix_alto"
      ],
      "score_social": null,
      "earnings_label": "No Data",
      "score_macro_adj": -8,
      "score_asymmetry": 0,
      "fundamental_inflection_score": 0,
      "catalyst_score": 0,
      "spinoff_score": 0,
      "insider_score": 0,
      "options_flow_score": 0,
      "options_cp_ratio": null,
      "insider_buys": 0,
      "convergence_count": 0,
      "state": "WATCH",
      "score_final": 28,
      "confidence_pct": 28,
      "bubble_level": "Bajo",
      "argumento_en_contra": "Sin objeción crítica detectada",
      "decision_final": "AVOID"
    }
  ],
  "news": [
    {
      "feed": "https://feeds.reuters.com/reuters/businessNews",
      "error": "<urlopen error [Errno 11001] getaddrinfo failed>",
      "items": []
    },
    {
      "feed": "https://feeds.reuters.com/reuters/technologyNews",
      "error": "<urlopen error [Errno 11001] getaddrinfo failed>",
      "items": []
    },
    {
      "feed": "https://www.marketwatch.com/rss/topstories",
      "items": [
        {
          "title": "Oracle’s stock surges. Here’s how it finally left the AI penalty box.",
          "title_es": "Oracle’s stock surges. Así es como finalmente salió del área de penalización de la IA.",
          "link": "https://www.marketwatch.com/story/oracles-stock-surges-heres-how-it-finally-left-the-ai-penalty-box-d1d73d39?mod=mw_rss_topstories",
          "pubDate": "Wed, 11 Mar 2026 14:58:00 GMT"
        },
        {
          "title": "‘I’m so screwed’: How can I afford to care for a mom with dementia and send my teen to college?",
          "title_es": "“Estoy tan jodida”: ¿Cómo puedo permitirme cuidar a una madre con demencia y enviar a mi hijo adolescente a la universidad?",
          "link": "https://www.marketwatch.com/story/im-so-screwed-how-can-i-afford-to-care-for-a-mom-with-dementia-and-send-my-teen-to-college-9d127f90?mod=mw_rss_topstories",
          "pubDate": "Wed, 11 Mar 2026 14:50:00 GMT"
        },
        {
          "title": "Uber’s stock rises as new Amazon robotaxi partnership is ‘a positive surprise’",
          "title_es": "Las acciones de Uber suben mientras la nueva asociación de robotaxi con Amazon es \"una sorpresa positiva\"",
          "link": "https://www.marketwatch.com/story/ubers-stock-rises-as-new-amazon-robotaxi-partnership-is-a-positive-surprise-675873a1?mod=mw_rss_topstories",
          "pubDate": "Wed, 11 Mar 2026 14:37:00 GMT"
        },
        {
          "title": "Oil futures edge up but stay under $100 a barrel as IEA unveils largest-ever release of reserves",
          "title_es": "Los futuros del petróleo suben pero se mantienen por debajo de los 100 dólares el barril mientras la AIE revela la mayor liberación de reservas jamás realizada",
          "link": "https://www.marketwatch.com/story/oil-futures-rise-as-traders-await-decision-on-reserves-3cd81485?mod=mw_rss_topstories",
          "pubDate": "Wed, 11 Mar 2026 14:28:00 GMT"
        },
        {
          "title": "Unreliable nursing-home ratings raise disturbing questions — leaving families at a dead end",
          "title_es": "Las calificaciones poco confiables de los hogares de ancianos plantean preguntas inquietantes y dejan a las familias en un callejón sin salida",
          "link": "https://www.marketwatch.com/story/new-research-on-nursing-home-ratings-raises-disturbing-questions-what-are-families-to-do-685da1ef?mod=mw_rss_topstories",
          "pubDate": "Wed, 11 Mar 2026 13:45:00 GMT"
        }
      ]
    },
    {
      "feed": "https://www.investing.com/rss/news_25.rss",
      "items": [
        {
          "title": "Meta unveils four custom AI chips for data center growth",
          "title_es": "Meta presenta cuatro chips de IA personalizados para el crecimiento del centro de datos",
          "link": "https://www.investing.com/news/stock-market-news/meta-unveils-four-custom-ai-chips-for-data-center-growth-4554956",
          "pubDate": "2026-03-11 14:48:01"
        },
        {
          "title": "Starboard builds $350 mln stake in CarMax, nominates board members; stock rises",
          "title_es": "Starboard adquiere una participación de 350 millones de dólares en CarMax y nombra miembros de la junta directiva; las acciones suben",
          "link": "https://www.investing.com/news/stock-market-news/starboard-builds-350-mln-stake-in-carmax-nominates-board-members-bloomberg-4553420",
          "pubDate": "2026-03-11 14:47:12"
        },
        {
          "title": "Judge has limited role in resolving US Halkbank criminal case, prosecutor says",
          "title_es": "El juez tiene un papel limitado en la resolución del caso penal de Halkbank en EE. UU., dice el fiscal",
          "link": "https://www.investing.com/news/stock-market-news/judge-asks-us-prosecutors-to-explain-resolution-to-halkbank-criminal-case-4554784",
          "pubDate": "2026-03-11 14:43:00"
        },
        {
          "title": "Campbell’s cuts annual forecasts as demand sags",
          "title_es": "Campbell's recorta sus previsiones anuales ante la caída de la demanda",
          "link": "https://www.investing.com/news/stock-market-news/campbells-cuts-annual-forecasts-amid-macroeconomic-pressures-4554193",
          "pubDate": "2026-03-11 14:36:33"
        },
        {
          "title": "Oracle, Yandex among market cap stock movers on Wednesday",
          "title_es": "Oracle y Yandex, entre los impulsores de la capitalización de mercado el miércoles",
          "link": "https://www.investing.com/news/stock-market-news/oracle-yandex-among-market-cap-stock-movers-on-wednesday-93CH-4554931",
          "pubDate": "2026-03-11 14:32:02"
        }
      ]
    }
  ],
  "social": [
    {
      "symbol": "QQQ",
      "messages_checked": 30,
      "bullish": 7,
      "bearish": 3,
      "sentiment_score": 40.0
    },
    {
      "symbol": "SPY",
      "messages_checked": 30,
      "bullish": 3,
      "bearish": 9,
      "sentiment_score": -50.0
    },
    {
      "symbol": "NVDA",
      "messages_checked": 30,
      "bullish": 6,
      "bearish": 8,
      "sentiment_score": -14.3
    },
    {
      "symbol": "MSFT",
      "messages_checked": 30,
      "bullish": 6,
      "bearish": 0,
      "sentiment_score": 100.0
    },
    {
      "symbol": "AMD",
      "messages_checked": 30,
      "bullish": 17,
      "bearish": 3,
      "sentiment_score": 70.0
    },
    {
      "symbol": "TSLA",
      "messages_checked": 30,
      "bullish": 10,
      "bearish": 8,
      "sentiment_score": 11.1
    },
    {
      "symbol": "META",
      "messages_checked": 30,
      "bullish": 5,
      "bearish": 4,
      "sentiment_score": 11.1
    },
    {
      "symbol": "JPM",
      "messages_checked": 30,
      "bullish": 1,
      "bearish": 10,
      "sentiment_score": -81.8
    }
  ],
  "earnings": [
    {
      "symbol": "AVGO",
      "source": "finnhub",
      "date": "2026-03-04",
      "eps_estimate": 2.068,
      "eps_actual": 2.05,
      "revenue_estimate": 19563982642,
      "revenue_actual": 19311000000
    }
  ],
  "options": [
    {
      "symbol": "QQQ",
      "error": "HTTP Error 401: Unauthorized",
      "call_oi": null,
      "put_oi": null,
      "cp_ratio": null
    },
    {
      "symbol": "SPY",
      "error": "HTTP Error 401: Unauthorized",
      "call_oi": null,
      "put_oi": null,
      "cp_ratio": null
    },
    {
      "symbol": "IWM",
      "error": "HTTP Error 401: Unauthorized",
      "call_oi": null,
      "put_oi": null,
      "cp_ratio": null
    },
    {
      "symbol": "GLD",
      "error": "HTTP Error 401: Unauthorized",
      "call_oi": null,
      "put_oi": null,
      "cp_ratio": null
    },
    {
      "symbol": "TLT",
      "error": "HTTP Error 401: Unauthorized",
      "call_oi": null,
      "put_oi": null,
      "cp_ratio": null
    },
    {
      "symbol": "XLF",
      "error": "HTTP Error 401: Unauthorized",
      "call_oi": null,
      "put_oi": null,
      "cp_ratio": null
    },
    {
      "symbol": "XLV",
      "error": "HTTP Error 401: Unauthorized",
      "call_oi": null,
      "put_oi": null,
      "cp_ratio": null
    },
    {
      "symbol": "XLE",
      "error": "HTTP Error 401: Unauthorized",
      "call_oi": null,
      "put_oi": null,
      "cp_ratio": null
    },
    {
      "symbol": "XLI",
      "error": "HTTP Error 401: Unauthorized",
      "call_oi": null,
      "put_oi": null,
      "cp_ratio": null
    },
    {
      "symbol": "NVDA",
      "error": "HTTP Error 401: Unauthorized",
      "call_oi": null,
      "put_oi": null,
      "cp_ratio": null
    },
    {
      "symbol": "MSFT",
      "error": "HTTP Error 401: Unauthorized",
      "call_oi": null,
      "put_oi": null,
      "cp_ratio": null
    },
    {
      "symbol": "AMZN",
      "error": "HTTP Error 401: Unauthorized",
      "call_oi": null,
      "put_oi": null,
      "cp_ratio": null
    },
    {
      "symbol": "META",
      "error": "HTTP Error 401: Unauthorized",
      "call_oi": null,
      "put_oi": null,
      "cp_ratio": null
    },
    {
      "symbol": "AMD",
      "error": "HTTP Error 401: Unauthorized",
      "call_oi": null,
      "put_oi": null,
      "cp_ratio": null
    },
    {
      "symbol": "TSLA",
      "error": "HTTP Error 401: Unauthorized",
      "call_oi": null,
      "put_oi": null,
      "cp_ratio": null
    },
    {
      "symbol": "AVGO",
      "error": "HTTP Error 401: Unauthorized",
      "call_oi": null,
      "put_oi": null,
      "cp_ratio": null
    },
    {
      "symbol": "AAPL",
      "error": "HTTP Error 401: Unauthorized",
      "call_oi": null,
      "put_oi": null,
      "cp_ratio": null
    },
    {
      "symbol": "GOOGL",
      "error": "HTTP Error 401: Unauthorized",
      "call_oi": null,
      "put_oi": null,
      "cp_ratio": null
    },
    {
      "symbol": "JPM",
      "error": "HTTP Error 401: Unauthorized",
      "call_oi": null,
      "put_oi": null,
      "cp_ratio": null
    },
    {
      "symbol": "UNH",
      "error": "HTTP Error 401: Unauthorized",
      "call_oi": null,
      "put_oi": null,
      "cp_ratio": null
    }
  ],
  "finviz_news": [
    {
      "symbol": "QQQ",
      "items": [
        {
          "title": "Home",
          "title_es": "Hogar",
          "link": "/"
        },
        {
          "title": "News",
          "title_es": "Noticias",
          "link": "/news.ashx"
        },
        {
          "title": "Screener",
          "title_es": "evaluador",
          "link": "/screener.ashx"
        }
      ]
    },
    {
      "symbol": "SPY",
      "items": [
        {
          "title": "Home",
          "title_es": "Hogar",
          "link": "/"
        },
        {
          "title": "News",
          "title_es": "Noticias",
          "link": "/news.ashx"
        },
        {
          "title": "Screener",
          "title_es": "evaluador",
          "link": "/screener.ashx"
        }
      ]
    },
    {
      "symbol": "IWM",
      "items": [
        {
          "title": "Home",
          "title_es": "Hogar",
          "link": "/"
        },
        {
          "title": "News",
          "title_es": "Noticias",
          "link": "/news.ashx"
        },
        {
          "title": "Screener",
          "title_es": "evaluador",
          "link": "/screener.ashx"
        }
      ]
    },
    {
      "symbol": "GLD",
      "items": [
        {
          "title": "Home",
          "title_es": "Hogar",
          "link": "/"
        },
        {
          "title": "News",
          "title_es": "Noticias",
          "link": "/news.ashx"
        },
        {
          "title": "Screener",
          "title_es": "evaluador",
          "link": "/screener.ashx"
        }
      ]
    },
    {
      "symbol": "TLT",
      "items": [
        {
          "title": "Home",
          "title_es": "Hogar",
          "link": "/"
        },
        {
          "title": "News",
          "title_es": "Noticias",
          "link": "/news.ashx"
        },
        {
          "title": "Screener",
          "title_es": "evaluador",
          "link": "/screener.ashx"
        }
      ]
    },
    {
      "symbol": "XLF",
      "items": [
        {
          "title": "Home",
          "title_es": "Hogar",
          "link": "/"
        },
        {
          "title": "News",
          "title_es": "Noticias",
          "link": "/news.ashx"
        },
        {
          "title": "Screener",
          "title_es": "evaluador",
          "link": "/screener.ashx"
        }
      ]
    },
    {
      "symbol": "XLV",
      "items": [
        {
          "title": "Home",
          "title_es": "Hogar",
          "link": "/"
        },
        {
          "title": "News",
          "title_es": "Noticias",
          "link": "/news.ashx"
        },
        {
          "title": "Screener",
          "title_es": "evaluador",
          "link": "/screener.ashx"
        }
      ]
    },
    {
      "symbol": "XLE",
      "items": [
        {
          "title": "Home",
          "title_es": "Hogar",
          "link": "/"
        },
        {
          "title": "News",
          "title_es": "Noticias",
          "link": "/news.ashx"
        },
        {
          "title": "Screener",
          "title_es": "evaluador",
          "link": "/screener.ashx"
        }
      ]
    }
  ],
  "insider_map": {
    "', DELAY, 1)\" onmouseout=\"UnTip()\">FDBC": {
      "insider_buys": 1,
      "insider_events": 1
    },
    "', DELAY, 1)\" onmouseout=\"UnTip()\">TPL": {
      "insider_buys": 1,
      "insider_events": 1
    },
    "', DELAY, 1)\" onmouseout=\"UnTip()\">GRNT": {
      "insider_buys": 1,
      "insider_events": 1
    },
    "', DELAY, 1)\" onmouseout=\"UnTip()\">RCG": {
      "insider_buys": 1,
      "insider_events": 1
    },
    "', DELAY, 1)\" onmouseout=\"UnTip()\">NXG": {
      "insider_buys": 1,
      "insider_events": 1
    },
    "', DELAY, 1)\" onmouseout=\"UnTip()\">INDV": {
      "insider_buys": 2,
      "insider_events": 2
    },
    "', DELAY, 1)\" onmouseout=\"UnTip()\">BWFG": {
      "insider_buys": 1,
      "insider_events": 1
    },
    "', DELAY, 1)\" onmouseout=\"UnTip()\">AFL": {
      "insider_buys": 0,
      "insider_events": 1
    },
    "', DELAY, 1)\" onmouseout=\"UnTip()\">ENTX": {
      "insider_buys": 1,
      "insider_events": 1
    },
    "', DELAY, 1)\" onmouseout=\"UnTip()\">RMD": {
      "insider_buys": 0,
      "insider_events": 1
    },
    "', DELAY, 1)\" onmouseout=\"UnTip()\">CSTM": {
      "insider_buys": 3,
      "insider_events": 9
    },
    "', DELAY, 1)\" onmouseout=\"UnTip()\">SOLV": {
      "insider_buys": 1,
      "insider_events": 1
    },
    "', DELAY, 1)\" onmouseout=\"UnTip()\">FOUR": {
      "insider_buys": 1,
      "insider_events": 1
    },
    "', DELAY, 1)\" onmouseout=\"UnTip()\">GRMN": {
      "insider_buys": 0,
      "insider_events": 1
    },
    "', DELAY, 1)\" onmouseout=\"UnTip()\">SBC": {
      "insider_buys": 0,
      "insider_events": 1
    },
    "', DELAY, 1)\" onmouseout=\"UnTip()\">FOXX": {
      "insider_buys": 0,
      "insider_events": 1
    },
    "', DELAY, 1)\" onmouseout=\"UnTip()\">FPH": {
      "insider_buys": 0,
      "insider_events": 1
    },
    "', DELAY, 1)\" onmouseout=\"UnTip()\">MCS": {
      "insider_buys": 0,
      "insider_events": 1
    },
    "', DELAY, 1)\" onmouseout=\"UnTip()\">ABOS": {
      "insider_buys": 0,
      "insider_events": 1
    },
    "', DELAY, 1)\" onmouseout=\"UnTip()\">AM": {
      "insider_buys": 0,
      "insider_events": 2
    },
    "', DELAY, 1)\" onmouseout=\"UnTip()\">MNKD": {
      "insider_buys": 1,
      "insider_events": 1
    },
    "', DELAY, 1)\" onmouseout=\"UnTip()\">AR": {
      "insider_buys": 0,
      "insider_events": 2
    },
    "', DELAY, 1)\" onmouseout=\"UnTip()\">GCT": {
      "insider_buys": 0,
      "insider_events": 1
    },
    "', DELAY, 1)\" onmouseout=\"UnTip()\">NTRA": {
      "insider_buys": 0,
      "insider_events": 1
    },
    "', DELAY, 1)\" onmouseout=\"UnTip()\">FSLR": {
      "insider_buys": 0,
      "insider_events": 11
    },
    "', DELAY, 1)\" onmouseout=\"UnTip()\">ADMA": {
      "insider_buys": 0,
      "insider_events": 1
    },
    "', DELAY, 1)\" onmouseout=\"UnTip()\">ENOV": {
      "insider_buys": 1,
      "insider_events": 1
    },
    "', DELAY, 1)\" onmouseout=\"UnTip()\">NAMS": {
      "insider_buys": 0,
      "insider_events": 1
    },
    "', DELAY, 1)\" onmouseout=\"UnTip()\">FLEX": {
      "insider_buys": 0,
      "insider_events": 1
    },
    "', DELAY, 1)\" onmouseout=\"UnTip()\">ACEL": {
      "insider_buys": 1,
      "insider_events": 3
    },
    "', DELAY, 1)\" onmouseout=\"UnTip()\">VICR": {
      "insider_buys": 0,
      "insider_events": 1
    },
    "', DELAY, 1)\" onmouseout=\"UnTip()\">OKLO": {
      "insider_buys": 0,
      "insider_events": 1
    },
    "', DELAY, 1)\" onmouseout=\"UnTip()\">ADPT": {
      "insider_buys": 0,
      "insider_events": 1
    },
    "', DELAY, 1)\" onmouseout=\"UnTip()\">LSCC": {
      "insider_buys": 0,
      "insider_events": 6
    },
    "', DELAY, 1)\" onmouseout=\"UnTip()\">TKO": {
      "insider_buys": 0,
      "insider_events": 1
    },
    "', DELAY, 1)\" onmouseout=\"UnTip()\">COLD": {
      "insider_buys": 0,
      "insider_events": 1
    },
    "', DELAY, 1)\" onmouseout=\"UnTip()\">THC": {
      "insider_buys": 0,
      "insider_events": 1
    },
    "', DELAY, 1)\" onmouseout=\"UnTip()\">CXDO": {
      "insider_buys": 0,
      "insider_events": 2
    },
    "', DELAY, 1)\" onmouseout=\"UnTip()\">SHC": {
      "insider_buys": 0,
      "insider_events": 2
    },
    "', DELAY, 1)\" onmouseout=\"UnTip()\">GO": {
      "insider_buys": 0,
      "insider_events": 4
    },
    "', DELAY, 1)\" onmouseout=\"UnTip()\">HUT": {
      "insider_buys": 0,
      "insider_events": 2
    },
    "', DELAY, 1)\" onmouseout=\"UnTip()\">WHWK": {
      "insider_buys": 0,
      "insider_events": 3
    },
    "', DELAY, 1)\" onmouseout=\"UnTip()\">LSAK": {
      "insider_buys": 0,
      "insider_events": 1
    },
    "', DELAY, 1)\" onmouseout=\"UnTip()\">SEMR": {
      "insider_buys": 0,
      "insider_events": 1
    },
    "', DELAY, 1)\" onmouseout=\"UnTip()\">SATS": {
      "insider_buys": 0,
      "insider_events": 1
    },
    "', DELAY, 1)\" onmouseout=\"UnTip()\">AXTI": {
      "insider_buys": 0,
      "insider_events": 1
    },
    "', DELAY, 1)\" onmouseout=\"UnTip()\">HALO": {
      "insider_buys": 0,
      "insider_events": 1
    },
    "', DELAY, 1)\" onmouseout=\"UnTip()\">ESTC": {
      "insider_buys": 0,
      "insider_events": 7
    },
    "', DELAY, 1)\" onmouseout=\"UnTip()\">DXPE": {
      "insider_buys": 0,
      "insider_events": 1
    },
    "', DELAY, 1)\" onmouseout=\"UnTip()\">CJMB": {
      "insider_buys": 1,
      "insider_events": 1
    },
    "', DELAY, 1)\" onmouseout=\"UnTip()\">ALHC": {
      "insider_buys": 0,
      "insider_events": 1
    },
    "', DELAY, 1)\" onmouseout=\"UnTip()\">GSIT": {
      "insider_buys": 0,
      "insider_events": 1
    },
    "', DELAY, 1)\" onmouseout=\"UnTip()\">VTRS": {
      "insider_buys": 1,
      "insider_events": 1
    },
    "', DELAY, 1)\" onmouseout=\"UnTip()\">RMNI": {
      "insider_buys": 0,
      "insider_events": 1
    },
    "', DELAY, 1)\" onmouseout=\"UnTip()\">AOSL": {
      "insider_buys": 1,
      "insider_events": 1
    },
    "', DELAY, 1)\" onmouseout=\"UnTip()\">AMRC": {
      "insider_buys": 0,
      "insider_events": 1
    },
    "', DELAY, 1)\" onmouseout=\"UnTip()\">INDI": {
      "insider_buys": 0,
      "insider_events": 1
    },
    "', DELAY, 1)\" onmouseout=\"UnTip()\">KALV": {
      "insider_buys": 0,
      "insider_events": 1
    }
  },
  "macro_regime": {
    "vix": 24.93,
    "dgs10": 4.12,
    "dxy": 119.491,
    "macro_adj": -8,
    "macro_reasons": [
      "macro_vix_alto"
    ]
  },
  "top_opportunities": [
    {
      "ticker": "XLE",
      "ok": true,
      "currency": "USD",
      "exchange": "PCX",
      "regularMarketPrice": 56.695,
      "previousClose": null,
      "lastCloseSeries": 56.69499969482422,
      "chg_5d_pct": 0.9,
      "chg_20d_pct": 5.81,
      "ema20": 55.144,
      "ema50": 52.258,
      "sma200": 45.728,
      "overextension_200d_pct": 23.98,
      "rsi14": 66.04,
      "bb_upper": 57.32,
      "bb_lower": 53.62,
      "rel_volume": 0.32,
      "breakout_20": false,
      "intraday_15m_bias": "alcista",
      "score_tech": 96,
      "score": 70,
      "reasons": [
        "momento_5d_positivo",
        "tendencia_20d_fuerte",
        "price_above_ema20",
        "ema20_above_ema50",
        "rsi_constructivo",
        "intraday_15m_alcista",
        "macro_vix_alto",
        "bubble_critical",
        "devil_advocate_active"
      ],
      "score_social": null,
      "earnings_label": "No Data",
      "score_macro_adj": -8,
      "score_asymmetry": 0,
      "fundamental_inflection_score": 0,
      "catalyst_score": 0,
      "spinoff_score": 0,
      "insider_score": 0,
      "options_flow_score": 0,
      "options_cp_ratio": null,
      "insider_buys": 0,
      "convergence_count": 1,
      "state": "WATCH",
      "score_final": 70,
      "confidence_pct": 70,
      "bubble_level": "Crítico",
      "argumento_en_contra": "Divergencia bajista: precio sube con volumen débil",
      "decision_final": "HOLD"
    },
    {
      "ticker": "AVGO",
      "ok": true,
      "currency": "USD",
      "exchange": "NMS",
      "regularMarketPrice": 342.96,
      "previousClose": null,
      "lastCloseSeries": 342.9599914550781,
      "chg_5d_pct": 8.01,
      "chg_20d_pct": 0.74,
      "ema20": 331.618,
      "ema50": 335.186,
      "sma200": 322.397,
      "overextension_200d_pct": 6.38,
      "rsi14": 57.4,
      "bb_upper": 347.932,
      "bb_lower": 312.659,
      "rel_volume": 0.21,
      "breakout_20": false,
      "intraday_15m_bias": "neutro",
      "score_tech": 79,
      "score": 57,
      "reasons": [
        "momento_5d_fuerte",
        "tendencia_20d_positiva",
        "universo_prioritario",
        "price_above_ema20",
        "ema20_below_ema50",
        "rsi_constructivo",
        "macro_vix_alto",
        "earnings_calendar_signal",
        "devil_advocate_active"
      ],
      "score_social": null,
      "earnings_label": "Earnings Miss/Inline",
      "score_macro_adj": -8,
      "score_asymmetry": 0,
      "fundamental_inflection_score": 0,
      "catalyst_score": 0,
      "spinoff_score": 0,
      "insider_score": 0,
      "options_flow_score": 0,
      "options_cp_ratio": null,
      "insider_buys": 0,
      "convergence_count": 1,
      "state": "WATCH",
      "score_final": 57,
      "confidence_pct": 57,
      "bubble_level": "Medio",
      "argumento_en_contra": "Divergencia bajista: precio sube con volumen débil",
      "decision_final": "AVOID"
    },
    {
      "ticker": "NVDA",
      "ok": true,
      "currency": "USD",
      "exchange": "NMS",
      "regularMarketPrice": 186.345,
      "previousClose": null,
      "lastCloseSeries": 186.34500122070312,
      "chg_5d_pct": 1.81,
      "chg_20d_pct": -1.16,
      "ema20": 184.603,
      "ema50": 184.997,
      "sma200": 176.909,
      "overextension_200d_pct": 5.33,
      "rsi14": 51.69,
      "bb_upper": 195.026,
      "bb_lower": 176.274,
      "rel_volume": 0.27,
      "breakout_20": false,
      "intraday_15m_bias": "alcista",
      "score_tech": 70,
      "score": 54,
      "reasons": [
        "momento_5d_positivo",
        "universo_prioritario",
        "price_above_ema20",
        "ema20_below_ema50",
        "rsi_constructivo",
        "intraday_15m_alcista",
        "macro_vix_alto",
        "devil_advocate_active"
      ],
      "score_social": -14.3,
      "earnings_label": "No Data",
      "score_macro_adj": -8,
      "score_asymmetry": 0,
      "fundamental_inflection_score": 0,
      "catalyst_score": 0,
      "spinoff_score": 0,
      "insider_score": 0,
      "options_flow_score": 0,
      "options_cp_ratio": null,
      "insider_buys": 0,
      "convergence_count": 1,
      "state": "WATCH",
      "score_final": 54,
      "confidence_pct": 54,
      "bubble_level": "Bajo",
      "argumento_en_contra": "Divergencia bajista: precio sube con volumen débil",
      "decision_final": "AVOID"
    },
    {
      "ticker": "AMD",
      "ok": true,
      "currency": "USD",
      "exchange": "NMS",
      "regularMarketPrice": 205.755,
      "previousClose": null,
      "lastCloseSeries": 205.7550048828125,
      "chg_5d_pct": 1.82,
      "chg_20d_pct": -3.66,
      "ema20": 204.934,
      "ema50": 211.883,
      "sma200": 189.991,
      "overextension_200d_pct": 8.3,
      "rsi14": 48.97,
      "bb_upper": 214.357,
      "bb_lower": 191.037,
      "rel_volume": 0.27,
      "breakout_20": false,
      "intraday_15m_bias": "neutro",
      "score_tech": 60,
      "score": 52,
      "reasons": [
        "momento_5d_positivo",
        "universo_prioritario",
        "price_above_ema20",
        "ema20_below_ema50",
        "macro_vix_alto",
        "social_bullish",
        "devil_advocate_active"
      ],
      "score_social": 70.0,
      "earnings_label": "No Data",
      "score_macro_adj": -8,
      "score_asymmetry": 0,
      "fundamental_inflection_score": 0,
      "catalyst_score": 0,
      "spinoff_score": 0,
      "insider_score": 0,
      "options_flow_score": 0,
      "options_cp_ratio": null,
      "insider_buys": 0,
      "convergence_count": 2,
      "state": "WATCH",
      "score_final": 52,
      "confidence_pct": 52,
      "bubble_level": "Bajo",
      "argumento_en_contra": "Divergencia bajista: precio sube con volumen débil",
      "decision_final": "AVOID"
    },
    {
      "ticker": "GLD",
      "ok": true,
      "currency": "USD",
      "exchange": "PCX",
      "regularMarketPrice": 475.93,
      "previousClose": null,
      "lastCloseSeries": 475.92999267578125,
      "chg_5d_pct": 0.88,
      "chg_20d_pct": 2.93,
      "ema20": 469.566,
      "ema50": 450.76,
      "sma200": 369.215,
      "overextension_200d_pct": 28.9,
      "rsi14": 55.3,
      "bb_upper": 490.494,
      "bb_lower": 449.78,
      "rel_volume": 0.22,
      "breakout_20": false,
      "intraday_15m_bias": "bajista",
      "score_tech": 76,
      "score": 50,
      "reasons": [
        "momento_5d_positivo",
        "tendencia_20d_positiva",
        "price_above_ema20",
        "ema20_above_ema50",
        "rsi_constructivo",
        "intraday_15m_bajista",
        "macro_vix_alto",
        "bubble_critical",
        "devil_advocate_active"
      ],
      "score_social": null,
      "earnings_label": "No Data",
      "score_macro_adj": -8,
      "score_asymmetry": 0,
      "fundamental_inflection_score": 0,
      "catalyst_score": 0,
      "spinoff_score": 0,
      "insider_score": 0,
      "options_flow_score": 0,
      "options_cp_ratio": null,
      "insider_buys": 0,
      "convergence_count": 1,
      "state": "WATCH",
      "score_final": 50,
      "confidence_pct": 50,
      "bubble_level": "Crítico",
      "argumento_en_contra": "Divergencia bajista: precio sube con volumen débil",
      "decision_final": "AVOID"
    }
  ]
}