{
  "generated_at": "2026-03-11T17:49:02Z",
  "macro": [
    {
      "series": "M2SL",
      "latest_date": "2026-01-01",
      "latest_value": "22442.1"
    },
    {
      "series": "DGS10",
      "latest_date": "2026-03-09",
      "latest_value": "4.12"
    },
    {
      "series": "DGS2",
      "latest_date": "2026-03-09",
      "latest_value": "3.56"
    },
    {
      "series": "DTWEXBGS",
      "latest_date": "2026-03-06",
      "latest_value": "119.4910"
    },
    {
      "series": "VIXCLS",
      "latest_date": "2026-03-10",
      "latest_value": "24.93"
    }
  ],
  "market": [
    {
      "ticker": "QQQ",
      "ok": true,
      "currency": "USD",
      "exchange": "NGM",
      "regularMarketPrice": 606.48,
      "previousClose": null,
      "lastCloseSeries": 606.47998046875,
      "chg_5d_pct": -0.7,
      "chg_20d_pct": -0.82,
      "ema20": 608.048,
      "ema50": 611.106,
      "sma200": 590.194,
      "overextension_200d_pct": 2.76,
      "rsi14": 47.96,
      "bb_upper": 615.148,
      "bb_lower": 597.714,
      "rel_volume": 0.6,
      "breakout_20": false,
      "intraday_15m_bias": "bajista",
      "score_tech": 37,
      "score": 29,
      "reasons": [
        "universo_prioritario",
        "price_below_ema20",
        "ema20_below_ema50",
        "intraday_15m_bajista",
        "macro_vix_alto"
      ],
      "score_social": -16.7,
      "earnings_label": "No Data",
      "score_macro_adj": -8,
      "score_asymmetry": 0,
      "fundamental_inflection_score": 0,
      "catalyst_score": 0,
      "spinoff_score": 0,
      "insider_score": 0,
      "options_flow_score": 0,
      "options_cp_ratio": null,
      "insider_buys": 0,
      "convergence_count": 0,
      "state": "WATCH",
      "score_final": 29,
      "confidence_pct": 29,
      "bubble_level": "Bajo",
      "argumento_en_contra": "Sin objeción crítica detectada",
      "decision_final": "AVOID"
    },
    {
      "ticker": "SPY",
      "ok": true,
      "currency": "USD",
      "exchange": "PCX",
      "regularMarketPrice": 674.6,
      "previousClose": null,
      "lastCloseSeries": 674.5999755859375,
      "chg_5d_pct": -1.54,
      "chg_20d_pct": -2.53,
      "ema20": 682.726,
      "ema50": 684.149,
      "sma200": 657.797,
      "overextension_200d_pct": 2.55,
      "rsi14": 41.47,
      "bb_upper": 694.255,
      "bb_lower": 672.924,
      "rel_volume": 0.48,
      "breakout_20": false,
      "intraday_15m_bias": "bajista",
      "score_tech": 33,
      "score": 25,
      "reasons": [
        "price_below_ema20",
        "ema20_below_ema50",
        "intraday_15m_bajista",
        "macro_vix_alto"
      ],
      "score_social": 0.0,
      "earnings_label": "No Data",
      "score_macro_adj": -8,
      "score_asymmetry": 0,
      "fundamental_inflection_score": 0,
      "catalyst_score": 0,
      "spinoff_score": 0,
      "insider_score": 0,
      "options_flow_score": 0,
      "options_cp_ratio": null,
      "insider_buys": 0,
      "convergence_count": 0,
      "state": "WATCH",
      "score_final": 25,
      "confidence_pct": 25,
      "bubble_level": "Bajo",
      "argumento_en_contra": "Sin objeción crítica detectada",
      "decision_final": "AVOID"
    },
    {
      "ticker": "IWM",
      "ok": true,
      "currency": "USD",
      "exchange": "PCX",
      "regularMarketPrice": 251.3,
      "previousClose": null,
      "lastCloseSeries": 251.3000030517578,
      "chg_5d_pct": -4.0,
      "chg_20d_pct": -5.58,
      "ema20": 258.837,
      "ema50": 258.47,
      "sma200": 239.774,
      "overextension_200d_pct": 4.81,
      "rsi14": 38.34,
      "bb_upper": 269.873,
      "bb_lower": 251.15,
      "rel_volume": 0.79,
      "breakout_20": false,
      "intraday_15m_bias": "bajista",
      "score_tech": 20,
      "score": 12,
      "reasons": [
        "momento_5d_debil",
        "tendencia_20d_debil",
        "price_below_ema20",
        "ema20_above_ema50",
        "intraday_15m_bajista",
        "macro_vix_alto"
      ],
      "score_social": null,
      "earnings_label": "No Data",
      "score_macro_adj": -8,
      "score_asymmetry": 0,
      "fundamental_inflection_score": 0,
      "catalyst_score": 0,
      "spinoff_score": 0,
      "insider_score": 0,
      "options_flow_score": 0,
      "options_cp_ratio": null,
      "insider_buys": 0,
      "convergence_count": 0,
      "state": "WATCH",
      "score_final": 12,
      "confidence_pct": 12,
      "bubble_level": "Bajo",
      "argumento_en_contra": "Sin objeción crítica detectada",
      "decision_final": "AVOID"
    },
    {
      "ticker": "GLD",
      "ok": true,
      "currency": "USD",
      "exchange": "PCX",
      "regularMarketPrice": 474.63,
      "previousClose": null,
      "lastCloseSeries": 474.6300048828125,
      "chg_5d_pct": 0.6,
      "chg_20d_pct": 2.64,
      "ema20": 469.442,
      "ema50": 450.709,
      "sma200": 369.208,
      "overextension_200d_pct": 28.55,
      "rsi14": 54.62,
      "bb_upper": 490.363,
      "bb_lower": 449.781,
      "rel_volume": 0.43,
      "breakout_20": false,
      "intraday_15m_bias": "bajista",
      "score_tech": 76,
      "score": 50,
      "reasons": [
        "momento_5d_positivo",
        "tendencia_20d_positiva",
        "price_above_ema20",
        "ema20_above_ema50",
        "rsi_constructivo",
        "intraday_15m_bajista",
        "macro_vix_alto",
        "bubble_critical",
        "devil_advocate_active"
      ],
      "score_social": null,
      "earnings_label": "No Data",
      "score_macro_adj": -8,
      "score_asymmetry": 0,
      "fundamental_inflection_score": 0,
      "catalyst_score": 0,
      "spinoff_score": 0,
      "insider_score": 0,
      "options_flow_score": 0,
      "options_cp_ratio": null,
      "insider_buys": 0,
      "convergence_count": 1,
      "state": "WATCH",
      "score_final": 50,
      "confidence_pct": 50,
      "bubble_level": "Crítico",
      "argumento_en_contra": "Divergencia bajista: precio sube con volumen débil",
      "decision_final": "AVOID"
    },
    {
      "ticker": "TLT",
      "ok": true,
      "currency": "USD",
      "exchange": "NGM",
      "regularMarketPrice": 87.225,
      "previousClose": null,
      "lastCloseSeries": 87.2249984741211,
      "chg_5d_pct": -2.16,
      "chg_20d_pct": -1.47,
      "ema20": 88.864,
      "ema50": 88.637,
      "sma200": 88.14,
      "overextension_200d_pct": -1.04,
      "rsi14": 37.91,
      "bb_upper": 90.915,
      "bb_lower": 87.71,
      "rel_volume": 0.81,
      "breakout_20": false,
      "intraday_15m_bias": "bajista",
      "score_tech": 31,
      "score": 23,
      "reasons": [
        "momento_5d_debil",
        "price_below_ema20",
        "ema20_above_ema50",
        "bollinger_breakdown",
        "intraday_15m_bajista",
        "macro_vix_alto"
      ],
      "score_social": null,
      "earnings_label": "No Data",
      "score_macro_adj": -8,
      "score_asymmetry": 0,
      "fundamental_inflection_score": 0,
      "catalyst_score": 0,
      "spinoff_score": 0,
      "insider_score": 0,
      "options_flow_score": 0,
      "options_cp_ratio": null,
      "insider_buys": 0,
      "convergence_count": 0,
      "state": "WATCH",
      "score_final": 23,
      "confidence_pct": 23,
      "bubble_level": "Bajo",
      "argumento_en_contra": "Sin objeción crítica detectada",
      "decision_final": "AVOID"
    },
    {
      "ticker": "XLF",
      "ok": true,
      "currency": "USD",
      "exchange": "PCX",
      "regularMarketPrice": 49.43,
      "previousClose": null,
      "lastCloseSeries": 49.43000030517578,
      "chg_5d_pct": -4.02,
      "chg_20d_pct": -7.69,
      "ema20": 51.411,
      "ema50": 52.471,
      "sma200": 52.835,
      "overextension_200d_pct": -6.44,
      "rsi14": 31.51,
      "bb_upper": 53.186,
      "bb_lower": 49.679,
      "rel_volume": 0.6,
      "breakout_20": false,
      "intraday_15m_bias": "bajista",
      "score_tech": 0,
      "score": 42,
      "reasons": [
        "momento_5d_debil",
        "tendencia_20d_debil",
        "price_below_ema20",
        "ema20_below_ema50",
        "rsi_debil",
        "bollinger_breakdown",
        "intraday_15m_bajista",
        "macro_vix_alto"
      ],
      "score_social": null,
      "earnings_label": "No Data",
      "score_macro_adj": -8,
      "score_asymmetry": 0,
      "fundamental_inflection_score": 0,
      "catalyst_score": 0,
      "spinoff_score": 0,
      "insider_score": 0,
      "options_flow_score": 0,
      "options_cp_ratio": null,
      "insider_buys": 0,
      "convergence_count": 0,
      "state": "WATCH",
      "score_final": 42,
      "confidence_pct": 42,
      "bubble_level": "Bajo",
      "argumento_en_contra": "Sin objeción crítica detectada",
      "decision_final": "AVOID"
    },
    {
      "ticker": "XLV",
      "ok": true,
      "currency": "USD",
      "exchange": "PCX",
      "regularMarketPrice": 152.58,
      "previousClose": null,
      "lastCloseSeries": 152.5800018310547,
      "chg_5d_pct": -2.85,
      "chg_20d_pct": -1.77,
      "ema20": 155.709,
      "ema50": 155.478,
      "sma200": 144.707,
      "overextension_200d_pct": 5.44,
      "rsi14": 39.29,
      "bb_upper": 160.591,
      "bb_lower": 152.391,
      "rel_volume": 0.6,
      "breakout_20": false,
      "intraday_15m_bias": "bajista",
      "score_tech": 35,
      "score": 27,
      "reasons": [
        "momento_5d_debil",
        "price_below_ema20",
        "ema20_above_ema50",
        "intraday_15m_bajista",
        "macro_vix_alto"
      ],
      "score_social": null,
      "earnings_label": "No Data",
      "score_macro_adj": -8,
      "score_asymmetry": 0,
      "fundamental_inflection_score": 0,
      "catalyst_score": 0,
      "spinoff_score": 0,
      "insider_score": 0,
      "options_flow_score": 0,
      "options_cp_ratio": null,
      "insider_buys": 0,
      "convergence_count": 0,
      "state": "WATCH",
      "score_final": 27,
      "confidence_pct": 27,
      "bubble_level": "Bajo",
      "argumento_en_contra": "Sin objeción crítica detectada",
      "decision_final": "AVOID"
    },
    {
      "ticker": "XLE",
      "ok": true,
      "currency": "USD",
      "exchange": "PCX",
      "regularMarketPrice": 56.665,
      "previousClose": null,
      "lastCloseSeries": 56.665000915527344,
      "chg_5d_pct": 0.85,
      "chg_20d_pct": 5.76,
      "ema20": 55.141,
      "ema50": 52.256,
      "sma200": 45.728,
      "overextension_200d_pct": 23.92,
      "rsi14": 65.91,
      "bb_upper": 57.315,
      "bb_lower": 53.623,
      "rel_volume": 0.5,
      "breakout_20": false,
      "intraday_15m_bias": "alcista",
      "score_tech": 96,
      "score": 70,
      "reasons": [
        "momento_5d_positivo",
        "tendencia_20d_fuerte",
        "price_above_ema20",
        "ema20_above_ema50",
        "rsi_constructivo",
        "intraday_15m_alcista",
        "macro_vix_alto",
        "bubble_critical",
        "devil_advocate_active"
      ],
      "score_social": null,
      "earnings_label": "No Data",
      "score_macro_adj": -8,
      "score_asymmetry": 0,
      "fundamental_inflection_score": 0,
      "catalyst_score": 0,
      "spinoff_score": 0,
      "insider_score": 0,
      "options_flow_score": 0,
      "options_cp_ratio": null,
      "insider_buys": 0,
      "convergence_count": 1,
      "state": "WATCH",
      "score_final": 70,
      "confidence_pct": 70,
      "bubble_level": "Crítico",
      "argumento_en_contra": "Divergencia bajista: precio sube con volumen débil",
      "decision_final": "HOLD"
    },
    {
      "ticker": "XLI",
      "ok": true,
      "currency": "USD",
      "exchange": "PCX",
      "regularMarketPrice": 169.41,
      "previousClose": null,
      "lastCloseSeries": 169.41000366210938,
      "chg_5d_pct": -3.73,
      "chg_20d_pct": -2.59,
      "ema20": 172.665,
      "ema50": 168.84,
      "sma200": 155.454,
      "overextension_200d_pct": 8.98,
      "rsi14": 43.27,
      "bb_upper": 179.795,
      "bb_lower": 169.143,
      "rel_volume": 0.68,
      "breakout_20": false,
      "intraday_15m_bias": "bajista",
      "score_tech": 35,
      "score": 27,
      "reasons": [
        "momento_5d_debil",
        "price_below_ema20",
        "ema20_above_ema50",
        "intraday_15m_bajista",
        "macro_vix_alto"
      ],
      "score_social": null,
      "earnings_label": "No Data",
      "score_macro_adj": -8,
      "score_asymmetry": 0,
      "fundamental_inflection_score": 0,
      "catalyst_score": 0,
      "spinoff_score": 0,
      "insider_score": 0,
      "options_flow_score": 0,
      "options_cp_ratio": null,
      "insider_buys": 0,
      "convergence_count": 0,
      "state": "WATCH",
      "score_final": 27,
      "confidence_pct": 27,
      "bubble_level": "Bajo",
      "argumento_en_contra": "Sin objeción crítica detectada",
      "decision_final": "AVOID"
    },
    {
      "ticker": "NVDA",
      "ok": true,
      "currency": "USD",
      "exchange": "NMS",
      "regularMarketPrice": 185.035,
      "previousClose": null,
      "lastCloseSeries": 185.03509521484375,
      "chg_5d_pct": 1.09,
      "chg_20d_pct": -1.86,
      "ema20": 184.479,
      "ema50": 184.945,
      "sma200": 176.903,
      "overextension_200d_pct": 4.6,
      "rsi14": 50.33,
      "bb_upper": 194.959,
      "bb_lower": 176.211,
      "rel_volume": 0.47,
      "breakout_20": false,
      "intraday_15m_bias": "bajista",
      "score_tech": 60,
      "score": 52,
      "reasons": [
        "momento_5d_positivo",
        "universo_prioritario",
        "price_above_ema20",
        "ema20_below_ema50",
        "rsi_constructivo",
        "intraday_15m_bajista",
        "macro_vix_alto",
        "social_bullish",
        "devil_advocate_active"
      ],
      "score_social": 50.0,
      "earnings_label": "No Data",
      "score_macro_adj": -8,
      "score_asymmetry": 0,
      "fundamental_inflection_score": 0,
      "catalyst_score": 0,
      "spinoff_score": 0,
      "insider_score": 0,
      "options_flow_score": 0,
      "options_cp_ratio": null,
      "insider_buys": 0,
      "convergence_count": 2,
      "state": "WATCH",
      "score_final": 52,
      "confidence_pct": 52,
      "bubble_level": "Bajo",
      "argumento_en_contra": "Divergencia bajista: precio sube con volumen débil",
      "decision_final": "AVOID"
    },
    {
      "ticker": "MSFT",
      "ok": true,
      "currency": "USD",
      "exchange": "NMS",
      "regularMarketPrice": 403.155,
      "previousClose": null,
      "lastCloseSeries": 403.1549987792969,
      "chg_5d_pct": -0.5,
      "chg_20d_pct": -2.45,
      "ema20": 407.126,
      "ema50": 427.743,
      "sma200": 483.819,
      "overextension_200d_pct": -16.67,
      "rsi14": 43.61,
      "bb_upper": 413.526,
      "bb_lower": 387.859,
      "rel_volume": 0.41,
      "breakout_20": false,
      "intraday_15m_bias": "bajista",
      "score_tech": 37,
      "score": 29,
      "reasons": [
        "universo_prioritario",
        "price_below_ema20",
        "ema20_below_ema50",
        "intraday_15m_bajista",
        "macro_vix_alto"
      ],
      "score_social": 20.0,
      "earnings_label": "No Data",
      "score_macro_adj": -8,
      "score_asymmetry": 0,
      "fundamental_inflection_score": 0,
      "catalyst_score": 0,
      "spinoff_score": 0,
      "insider_score": 0,
      "options_flow_score": 0,
      "options_cp_ratio": null,
      "insider_buys": 0,
      "convergence_count": 0,
      "state": "WATCH",
      "score_final": 29,
      "confidence_pct": 29,
      "bubble_level": "Bajo",
      "argumento_en_contra": "Sin objeción crítica detectada",
      "decision_final": "AVOID"
    },
    {
      "ticker": "AMZN",
      "ok": true,
      "currency": "USD",
      "exchange": "NMS",
      "regularMarketPrice": 212.09,
      "previousClose": null,
      "lastCloseSeries": 212.08999633789062,
      "chg_5d_pct": -2.18,
      "chg_20d_pct": 2.48,
      "ema20": 213.422,
      "ema50": 219.546,
      "sma200": 224.642,
      "overextension_200d_pct": -5.59,
      "rsi14": 46.23,
      "bb_upper": 219.231,
      "bb_lower": 197.946,
      "rel_volume": 0.37,
      "breakout_20": false,
      "intraday_15m_bias": "bajista",
      "score_tech": 35,
      "score": 27,
      "reasons": [
        "momento_5d_debil",
        "tendencia_20d_positiva",
        "universo_prioritario",
        "price_below_ema20",
        "ema20_below_ema50",
        "intraday_15m_bajista",
        "macro_vix_alto"
      ],
      "score_social": null,
      "earnings_label": "No Data",
      "score_macro_adj": -8,
      "score_asymmetry": 0,
      "fundamental_inflection_score": 0,
      "catalyst_score": 0,
      "spinoff_score": 0,
      "insider_score": 0,
      "options_flow_score": 0,
      "options_cp_ratio": null,
      "insider_buys": 0,
      "convergence_count": 0,
      "state": "WATCH",
      "score_final": 27,
      "confidence_pct": 27,
      "bubble_level": "Bajo",
      "argumento_en_contra": "Sin objeción crítica detectada",
      "decision_final": "AVOID"
    },
    {
      "ticker": "META",
      "ok": true,
      "currency": "USD",
      "exchange": "NMS",
      "regularMarketPrice": 652.13,
      "previousClose": null,
      "lastCloseSeries": 652.1300048828125,
      "chg_5d_pct": -2.34,
      "chg_20d_pct": -2.77,
      "ema20": 654.105,
      "ema50": 656.63,
      "sma200": 691.723,
      "overextension_200d_pct": -5.72,
      "rsi14": 48.79,
      "bb_upper": 668.088,
      "bb_lower": 633.116,
      "rel_volume": 0.4,
      "breakout_20": false,
      "intraday_15m_bias": "bajista",
      "score_tech": 27,
      "score": 19,
      "reasons": [
        "momento_5d_debil",
        "universo_prioritario",
        "price_below_ema20",
        "ema20_below_ema50",
        "intraday_15m_bajista",
        "macro_vix_alto"
      ],
      "score_social": 16.7,
      "earnings_label": "No Data",
      "score_macro_adj": -8,
      "score_asymmetry": 0,
      "fundamental_inflection_score": 0,
      "catalyst_score": 0,
      "spinoff_score": 0,
      "insider_score": 0,
      "options_flow_score": 0,
      "options_cp_ratio": null,
      "insider_buys": 0,
      "convergence_count": 0,
      "state": "WATCH",
      "score_final": 19,
      "confidence_pct": 19,
      "bubble_level": "Bajo",
      "argumento_en_contra": "Sin objeción crítica detectada",
      "decision_final": "AVOID"
    },
    {
      "ticker": "AMD",
      "ok": true,
      "currency": "USD",
      "exchange": "NMS",
      "regularMarketPrice": 204.6,
      "previousClose": null,
      "lastCloseSeries": 204.60000610351562,
      "chg_5d_pct": 1.25,
      "chg_20d_pct": -4.2,
      "ema20": 204.824,
      "ema50": 211.838,
      "sma200": 189.986,
      "overextension_200d_pct": 7.69,
      "rsi14": 48.24,
      "bb_upper": 214.249,
      "bb_lower": 191.029,
      "rel_volume": 0.43,
      "breakout_20": false,
      "intraday_15m_bias": "bajista",
      "score_tech": 43,
      "score": 27,
      "reasons": [
        "momento_5d_positivo",
        "universo_prioritario",
        "price_below_ema20",
        "ema20_below_ema50",
        "intraday_15m_bajista",
        "macro_vix_alto",
        "devil_advocate_active"
      ],
      "score_social": 20.0,
      "earnings_label": "No Data",
      "score_macro_adj": -8,
      "score_asymmetry": 0,
      "fundamental_inflection_score": 0,
      "catalyst_score": 0,
      "spinoff_score": 0,
      "insider_score": 0,
      "options_flow_score": 0,
      "options_cp_ratio": null,
      "insider_buys": 0,
      "convergence_count": 0,
      "state": "WATCH",
      "score_final": 27,
      "confidence_pct": 27,
      "bubble_level": "Bajo",
      "argumento_en_contra": "Divergencia bajista: precio sube con volumen débil",
      "decision_final": "AVOID"
    },
    {
      "ticker": "TSLA",
      "ok": true,
      "currency": "USD",
      "exchange": "NMS",
      "regularMarketPrice": 405.701,
      "previousClose": null,
      "lastCloseSeries": 405.7012023925781,
      "chg_5d_pct": -0.06,
      "chg_20d_pct": -4.59,
      "ema20": 407.499,
      "ema50": 418.651,
      "sma200": 393.019,
      "overextension_200d_pct": 3.23,
      "rsi14": 46.86,
      "bb_upper": 424.317,
      "bb_lower": 391.038,
      "rel_volume": 0.8,
      "breakout_20": false,
      "intraday_15m_bias": "neutro",
      "score_tech": 38,
      "score": 38,
      "reasons": [
        "price_below_ema20",
        "ema20_below_ema50",
        "macro_vix_alto",
        "social_bullish"
      ],
      "score_social": 57.1,
      "earnings_label": "No Data",
      "score_macro_adj": -8,
      "score_asymmetry": 0,
      "fundamental_inflection_score": 0,
      "catalyst_score": 0,
      "spinoff_score": 0,
      "insider_score": 0,
      "options_flow_score": 0,
      "options_cp_ratio": null,
      "insider_buys": 0,
      "convergence_count": 1,
      "state": "WATCH",
      "score_final": 38,
      "confidence_pct": 38,
      "bubble_level": "Bajo",
      "argumento_en_contra": "Sin objeción crítica detectada",
      "decision_final": "AVOID"
    },
    {
      "ticker": "AVGO",
      "ok": true,
      "currency": "USD",
      "exchange": "NMS",
      "regularMarketPrice": 339.505,
      "previousClose": null,
      "lastCloseSeries": 339.5050048828125,
      "chg_5d_pct": 6.92,
      "chg_20d_pct": -0.27,
      "ema20": 331.289,
      "ema50": 335.051,
      "sma200": 322.38,
      "overextension_200d_pct": 5.31,
      "rsi14": 55.07,
      "bb_upper": 347.322,
      "bb_lower": 312.924,
      "rel_volume": 0.39,
      "breakout_20": false,
      "intraday_15m_bias": "bajista",
      "score_tech": 66,
      "score": 44,
      "reasons": [
        "momento_5d_fuerte",
        "universo_prioritario",
        "price_above_ema20",
        "ema20_below_ema50",
        "rsi_constructivo",
        "intraday_15m_bajista",
        "macro_vix_alto",
        "earnings_calendar_signal",
        "devil_advocate_active"
      ],
      "score_social": null,
      "earnings_label": "Earnings Miss/Inline",
      "score_macro_adj": -8,
      "score_asymmetry": 0,
      "fundamental_inflection_score": 0,
      "catalyst_score": 0,
      "spinoff_score": 0,
      "insider_score": 0,
      "options_flow_score": 0,
      "options_cp_ratio": null,
      "insider_buys": 0,
      "convergence_count": 1,
      "state": "WATCH",
      "score_final": 44,
      "confidence_pct": 44,
      "bubble_level": "Medio",
      "argumento_en_contra": "Divergencia bajista: precio sube con volumen débil",
      "decision_final": "AVOID"
    },
    {
      "ticker": "AAPL",
      "ok": true,
      "currency": "USD",
      "exchange": "NMS",
      "regularMarketPrice": 260.25,
      "previousClose": null,
      "lastCloseSeries": 260.25,
      "chg_5d_pct": -0.86,
      "chg_20d_pct": -4.91,
      "ema20": 263.587,
      "ema50": 264.568,
      "sma200": 245.029,
      "overextension_200d_pct": 6.21,
      "rsi14": 44.75,
      "bb_upper": 274.982,
      "bb_lower": 253.596,
      "rel_volume": 0.26,
      "breakout_20": false,
      "intraday_15m_bias": "bajista",
      "score_tech": 33,
      "score": 25,
      "reasons": [
        "price_below_ema20",
        "ema20_below_ema50",
        "intraday_15m_bajista",
        "macro_vix_alto"
      ],
      "score_social": null,
      "earnings_label": "No Data",
      "score_macro_adj": -8,
      "score_asymmetry": 0,
      "fundamental_inflection_score": 0,
      "catalyst_score": 0,
      "spinoff_score": 0,
      "insider_score": 0,
      "options_flow_score": 0,
      "options_cp_ratio": null,
      "insider_buys": 0,
      "convergence_count": 0,
      "state": "WATCH",
      "score_final": 25,
      "confidence_pct": 25,
      "bubble_level": "Bajo",
      "argumento_en_contra": "Sin objeción crítica detectada",
      "decision_final": "AVOID"
    },
    {
      "ticker": "GOOGL",
      "ok": true,
      "currency": "USD",
      "exchange": "NMS",
      "regularMarketPrice": 308.6,
      "previousClose": null,
      "lastCloseSeries": 308.6000061035156,
      "chg_5d_pct": 1.8,
      "chg_20d_pct": -3.13,
      "ema20": 309.317,
      "ema50": 311.808,
      "sma200": 255.148,
      "overextension_200d_pct": 20.95,
      "rsi14": 47.13,
      "bb_upper": 315.527,
      "bb_lower": 298.265,
      "rel_volume": 0.38,
      "breakout_20": false,
      "intraday_15m_bias": "neutro",
      "score_tech": 44,
      "score": 18,
      "reasons": [
        "momento_5d_positivo",
        "price_below_ema20",
        "ema20_below_ema50",
        "macro_vix_alto",
        "bubble_critical",
        "devil_advocate_active"
      ],
      "score_social": null,
      "earnings_label": "No Data",
      "score_macro_adj": -8,
      "score_asymmetry": 0,
      "fundamental_inflection_score": 0,
      "catalyst_score": 0,
      "spinoff_score": 0,
      "insider_score": 0,
      "options_flow_score": 0,
      "options_cp_ratio": null,
      "insider_buys": 0,
      "convergence_count": 0,
      "state": "WATCH",
      "score_final": 18,
      "confidence_pct": 18,
      "bubble_level": "Crítico",
      "argumento_en_contra": "Divergencia bajista: precio sube con volumen débil",
      "decision_final": "AVOID"
    },
    {
      "ticker": "JPM",
      "ok": true,
      "currency": "USD",
      "exchange": "NYQ",
      "regularMarketPrice": 285.76,
      "previousClose": null,
      "lastCloseSeries": 285.7601013183594,
      "chg_5d_pct": -4.55,
      "chg_20d_pct": -10.22,
      "ema20": 298.619,
      "ema50": 304.986,
      "sma200": 300.518,
      "overextension_200d_pct": -4.91,
      "rsi14": 33.46,
      "bb_upper": 314.777,
      "bb_lower": 285.234,
      "rel_volume": 0.41,
      "breakout_20": false,
      "intraday_15m_bias": "bajista",
      "score_tech": 3,
      "score": 0,
      "reasons": [
        "momento_5d_debil",
        "tendencia_20d_debil",
        "price_below_ema20",
        "ema20_below_ema50",
        "rsi_debil",
        "intraday_15m_bajista",
        "macro_vix_alto"
      ],
      "score_social": -23.1,
      "earnings_label": "No Data",
      "score_macro_adj": -8,
      "score_asymmetry": 0,
      "fundamental_inflection_score": 0,
      "catalyst_score": 0,
      "spinoff_score": 0,
      "insider_score": 0,
      "options_flow_score": 0,
      "options_cp_ratio": null,
      "insider_buys": 0,
      "convergence_count": 0,
      "state": "WATCH",
      "score_final": 0,
      "confidence_pct": 0,
      "bubble_level": "Bajo",
      "argumento_en_contra": "Sin objeción crítica detectada",
      "decision_final": "AVOID"
    },
    {
      "ticker": "UNH",
      "ok": true,
      "currency": "USD",
      "exchange": "NYQ",
      "regularMarketPrice": 283.08,
      "previousClose": null,
      "lastCloseSeries": 283.0799865722656,
      "chg_5d_pct": -3.04,
      "chg_20d_pct": 3.61,
      "ema20": 288.488,
      "ema50": 300.408,
      "sma200": 314.829,
      "overextension_200d_pct": -10.08,
      "rsi14": 42.87,
      "bb_upper": 296.89,
      "bb_lower": 276.715,
      "rel_volume": 0.38,
      "breakout_20": false,
      "intraday_15m_bias": "neutro",
      "score_tech": 36,
      "score": 28,
      "reasons": [
        "momento_5d_debil",
        "tendencia_20d_positiva",
        "price_below_ema20",
        "ema20_below_ema50",
        "macro_vix_alto"
      ],
      "score_social": null,
      "earnings_label": "No Data",
      "score_macro_adj": -8,
      "score_asymmetry": 0,
      "fundamental_inflection_score": 0,
      "catalyst_score": 0,
      "spinoff_score": 0,
      "insider_score": 0,
      "options_flow_score": 0,
      "options_cp_ratio": null,
      "insider_buys": 0,
      "convergence_count": 0,
      "state": "WATCH",
      "score_final": 28,
      "confidence_pct": 28,
      "bubble_level": "Bajo",
      "argumento_en_contra": "Sin objeción crítica detectada",
      "decision_final": "AVOID"
    }
  ],
  "news": [
    {
      "feed": "https://feeds.reuters.com/reuters/businessNews",
      "error": "<urlopen error [Errno 11001] getaddrinfo failed>",
      "items": []
    },
    {
      "feed": "https://feeds.reuters.com/reuters/technologyNews",
      "error": "<urlopen error [Errno 11001] getaddrinfo failed>",
      "items": []
    },
    {
      "feed": "https://www.marketwatch.com/rss/topstories",
      "items": [
        {
          "title": "Defense stocks are the market’s newest safe havens — and this ETF is a pure play",
          "title_es": "Las acciones de defensa son los refugios seguros más nuevos del mercado, y este ETF es un juego puro",
          "link": "https://www.marketwatch.com/story/why-defense-stocks-are-the-markets-newest-safe-havens-and-this-etf-is-a-pure-play-493a36e7?mod=mw_rss_topstories",
          "pubDate": "Wed, 11 Mar 2026 17:22:00 GMT"
        },
        {
          "title": "‘My mother refuses to turn on the heat’: Will America’s war with Iran really push up our utility bills?",
          "title_es": "“Mi madre se niega a encender la calefacción”: ¿La guerra de Estados Unidos con Irán realmente aumentará nuestras facturas de servicios públicos?",
          "link": "https://www.marketwatch.com/story/my-mother-refuses-to-turn-on-the-heat-will-americas-war-with-iran-really-push-up-our-utility-bills-df746548?mod=mw_rss_topstories",
          "pubDate": "Wed, 11 Mar 2026 17:21:00 GMT"
        },
        {
          "title": "Campbell’s stock heads toward a 23-year low, as it warns of more price cuts to recharge demand",
          "title_es": "Las acciones de Campbell se dirigen hacia un mínimo de 23 años, mientras advierte sobre más recortes de precios para recargar la demanda",
          "link": "https://www.marketwatch.com/story/campbells-stock-heads-toward-a-23-year-low-as-soups-and-snack-sales-are-down-again-bdefa664?mod=mw_rss_topstories",
          "pubDate": "Wed, 11 Mar 2026 17:14:00 GMT"
        },
        {
          "title": "‘He has been emotionally abusive’: My father, 75, is on oxygen and destitute. What do I owe him?",
          "title_es": "“Ha sido abusivo emocionalmente”: Mi padre, de 75 años, está con oxígeno y en la indigencia. ¿Qué le debo?",
          "link": "https://www.marketwatch.com/story/he-has-been-emotionally-abusive-my-father-75-is-on-oxygen-and-destitute-what-do-i-owe-him-eb21e873?mod=mw_rss_topstories",
          "pubDate": "Wed, 11 Mar 2026 17:00:00 GMT"
        },
        {
          "title": "Crude oil is trading like a ‘meme stock,’ these charts show",
          "title_es": "El petróleo crudo se cotiza como una “acción meme”, según muestran estos gráficos",
          "link": "https://www.marketwatch.com/story/crude-oil-is-trading-like-a-meme-stock-these-charts-show-2999d3c7?mod=mw_rss_topstories",
          "pubDate": "Wed, 11 Mar 2026 16:53:00 GMT"
        }
      ]
    },
    {
      "feed": "https://www.investing.com/rss/news_25.rss",
      "items": [
        {
          "title": "Pacira BioSciences shares rise 2% as activist pushes for CEO removal",
          "title_es": "Las acciones de Pacira BioSciences suben un 2% mientras un activista presiona para la destitución del director ejecutivo",
          "link": "https://www.investing.com/news/stock-market-news/pacira-biosciences-shares-rise-2-as-activist-pushes-for-ceo-removal-93CH-4555256",
          "pubDate": "2026-03-11 17:45:07"
        },
        {
          "title": "European shares fall again as Mideast tensions keep investors on edge",
          "title_es": "Las bolsas europeas vuelven a caer mientras las tensiones en Medio Oriente mantienen nerviosos a los inversores",
          "link": "https://www.investing.com/news/stock-market-news/european-shares-fall-as-mideast-tensions-keep-investors-on-edge-4553706",
          "pubDate": "2026-03-11 17:43:22"
        },
        {
          "title": "Solid Biosciences shares fall after gene therapy trial data",
          "title_es": "Las acciones de Solid Biosciences caen tras los datos del ensayo de terapia génica",
          "link": "https://www.investing.com/news/stock-market-news/solid-biosciences-shares-fall-after-gene-therapy-trial-data-93CH-4555247",
          "pubDate": "2026-03-11 17:37:32"
        },
        {
          "title": "CVS’ Aetna pays $117.7 million to settle US claims it defrauded Medicare",
          "title_es": "Aetna de CVS paga 117,7 millones de dólares para resolver acusaciones estadounidenses de defraudación a Medicare",
          "link": "https://www.investing.com/news/stock-market-news/cvs-aetna-pays-1177-million-to-settle-us-claims-it-defrauded-medicare-4555244",
          "pubDate": "2026-03-11 17:36:31"
        },
        {
          "title": "FCC chair criticizes slow pace of Amazon satellite launches",
          "title_es": "El presidente de la FCC critica la lentitud de los lanzamientos de satélites de Amazon",
          "link": "https://www.investing.com/news/stock-market-news/fcc-chair-criticizes-slow-pace-of-amazon-satellite-launches-4555233",
          "pubDate": "2026-03-11 17:24:29"
        }
      ]
    }
  ],
  "social": [
    {
      "symbol": "QQQ",
      "messages_checked": 30,
      "bullish": 5,
      "bearish": 7,
      "sentiment_score": -16.7
    },
    {
      "symbol": "SPY",
      "messages_checked": 30,
      "bullish": 5,
      "bearish": 5,
      "sentiment_score": 0.0
    },
    {
      "symbol": "NVDA",
      "messages_checked": 30,
      "bullish": 12,
      "bearish": 4,
      "sentiment_score": 50.0
    },
    {
      "symbol": "MSFT",
      "messages_checked": 30,
      "bullish": 6,
      "bearish": 4,
      "sentiment_score": 20.0
    },
    {
      "symbol": "AMD",
      "messages_checked": 30,
      "bullish": 6,
      "bearish": 4,
      "sentiment_score": 20.0
    },
    {
      "symbol": "TSLA",
      "messages_checked": 30,
      "bullish": 11,
      "bearish": 3,
      "sentiment_score": 57.1
    },
    {
      "symbol": "META",
      "messages_checked": 30,
      "bullish": 7,
      "bearish": 5,
      "sentiment_score": 16.7
    },
    {
      "symbol": "JPM",
      "messages_checked": 30,
      "bullish": 5,
      "bearish": 8,
      "sentiment_score": -23.1
    }
  ],
  "earnings": [
    {
      "symbol": "AVGO",
      "source": "finnhub",
      "date": "2026-03-04",
      "eps_estimate": 2.068,
      "eps_actual": 2.05,
      "revenue_estimate": 19563982642,
      "revenue_actual": 19311000000
    }
  ],
  "options": [
    {
      "symbol": "QQQ",
      "error": "HTTP Error 401: Unauthorized",
      "call_oi": null,
      "put_oi": null,
      "cp_ratio": null
    },
    {
      "symbol": "SPY",
      "error": "HTTP Error 401: Unauthorized",
      "call_oi": null,
      "put_oi": null,
      "cp_ratio": null
    },
    {
      "symbol": "IWM",
      "error": "HTTP Error 401: Unauthorized",
      "call_oi": null,
      "put_oi": null,
      "cp_ratio": null
    },
    {
      "symbol": "GLD",
      "error": "HTTP Error 401: Unauthorized",
      "call_oi": null,
      "put_oi": null,
      "cp_ratio": null
    },
    {
      "symbol": "TLT",
      "error": "HTTP Error 401: Unauthorized",
      "call_oi": null,
      "put_oi": null,
      "cp_ratio": null
    },
    {
      "symbol": "XLF",
      "error": "HTTP Error 401: Unauthorized",
      "call_oi": null,
      "put_oi": null,
      "cp_ratio": null
    },
    {
      "symbol": "XLV",
      "error": "HTTP Error 401: Unauthorized",
      "call_oi": null,
      "put_oi": null,
      "cp_ratio": null
    },
    {
      "symbol": "XLE",
      "error": "HTTP Error 401: Unauthorized",
      "call_oi": null,
      "put_oi": null,
      "cp_ratio": null
    },
    {
      "symbol": "XLI",
      "error": "HTTP Error 401: Unauthorized",
      "call_oi": null,
      "put_oi": null,
      "cp_ratio": null
    },
    {
      "symbol": "NVDA",
      "error": "HTTP Error 401: Unauthorized",
      "call_oi": null,
      "put_oi": null,
      "cp_ratio": null
    },
    {
      "symbol": "MSFT",
      "error": "HTTP Error 401: Unauthorized",
      "call_oi": null,
      "put_oi": null,
      "cp_ratio": null
    },
    {
      "symbol": "AMZN",
      "error": "HTTP Error 401: Unauthorized",
      "call_oi": null,
      "put_oi": null,
      "cp_ratio": null
    },
    {
      "symbol": "META",
      "error": "HTTP Error 401: Unauthorized",
      "call_oi": null,
      "put_oi": null,
      "cp_ratio": null
    },
    {
      "symbol": "AMD",
      "error": "HTTP Error 401: Unauthorized",
      "call_oi": null,
      "put_oi": null,
      "cp_ratio": null
    },
    {
      "symbol": "TSLA",
      "error": "HTTP Error 401: Unauthorized",
      "call_oi": null,
      "put_oi": null,
      "cp_ratio": null
    },
    {
      "symbol": "AVGO",
      "error": "HTTP Error 401: Unauthorized",
      "call_oi": null,
      "put_oi": null,
      "cp_ratio": null
    },
    {
      "symbol": "AAPL",
      "error": "HTTP Error 401: Unauthorized",
      "call_oi": null,
      "put_oi": null,
      "cp_ratio": null
    },
    {
      "symbol": "GOOGL",
      "error": "HTTP Error 401: Unauthorized",
      "call_oi": null,
      "put_oi": null,
      "cp_ratio": null
    },
    {
      "symbol": "JPM",
      "error": "HTTP Error 401: Unauthorized",
      "call_oi": null,
      "put_oi": null,
      "cp_ratio": null
    },
    {
      "symbol": "UNH",
      "error": "HTTP Error 401: Unauthorized",
      "call_oi": null,
      "put_oi": null,
      "cp_ratio": null
    }
  ],
  "finviz_news": [
    {
      "symbol": "QQQ",
      "items": [
        {
          "title": "Home",
          "title_es": "Hogar",
          "link": "/"
        },
        {
          "title": "News",
          "title_es": "Noticias",
          "link": "/news.ashx"
        },
        {
          "title": "Screener",
          "title_es": "evaluador",
          "link": "/screener.ashx"
        }
      ]
    },
    {
      "symbol": "SPY",
      "items": [
        {
          "title": "Home",
          "title_es": "Hogar",
          "link": "/"
        },
        {
          "title": "News",
          "title_es": "Noticias",
          "link": "/news.ashx"
        },
        {
          "title": "Screener",
          "title_es": "evaluador",
          "link": "/screener.ashx"
        }
      ]
    },
    {
      "symbol": "IWM",
      "items": [
        {
          "title": "Home",
          "title_es": "Hogar",
          "link": "/"
        },
        {
          "title": "News",
          "title_es": "Noticias",
          "link": "/news.ashx"
        },
        {
          "title": "Screener",
          "title_es": "evaluador",
          "link": "/screener.ashx"
        }
      ]
    },
    {
      "symbol": "GLD",
      "items": [
        {
          "title": "Home",
          "title_es": "Hogar",
          "link": "/"
        },
        {
          "title": "News",
          "title_es": "Noticias",
          "link": "/news.ashx"
        },
        {
          "title": "Screener",
          "title_es": "evaluador",
          "link": "/screener.ashx"
        }
      ]
    },
    {
      "symbol": "TLT",
      "items": [
        {
          "title": "Home",
          "title_es": "Hogar",
          "link": "/"
        },
        {
          "title": "News",
          "title_es": "Noticias",
          "link": "/news.ashx"
        },
        {
          "title": "Screener",
          "title_es": "evaluador",
          "link": "/screener.ashx"
        }
      ]
    },
    {
      "symbol": "XLF",
      "items": [
        {
          "title": "Home",
          "title_es": "Hogar",
          "link": "/"
        },
        {
          "title": "News",
          "title_es": "Noticias",
          "link": "/news.ashx"
        },
        {
          "title": "Screener",
          "title_es": "evaluador",
          "link": "/screener.ashx"
        }
      ]
    },
    {
      "symbol": "XLV",
      "items": [
        {
          "title": "Home",
          "title_es": "Hogar",
          "link": "/"
        },
        {
          "title": "News",
          "title_es": "Noticias",
          "link": "/news.ashx"
        },
        {
          "title": "Screener",
          "title_es": "evaluador",
          "link": "/screener.ashx"
        }
      ]
    },
    {
      "symbol": "XLE",
      "items": [
        {
          "title": "Home",
          "title_es": "Hogar",
          "link": "/"
        },
        {
          "title": "News",
          "title_es": "Noticias",
          "link": "/news.ashx"
        },
        {
          "title": "Screener",
          "title_es": "evaluador",
          "link": "/screener.ashx"
        }
      ]
    }
  ],
  "insider_map": {
    "', DELAY, 1)\" onmouseout=\"UnTip()\">VICR": {
      "insider_buys": 0,
      "insider_events": 2
    },
    "', DELAY, 1)\" onmouseout=\"UnTip()\">ISRG": {
      "insider_buys": 0,
      "insider_events": 1
    },
    "', DELAY, 1)\" onmouseout=\"UnTip()\">RMBS": {
      "insider_buys": 0,
      "insider_events": 1
    },
    "', DELAY, 1)\" onmouseout=\"UnTip()\">FFIN": {
      "insider_buys": 1,
      "insider_events": 1
    },
    "', DELAY, 1)\" onmouseout=\"UnTip()\">GAIA": {
      "insider_buys": 1,
      "insider_events": 1
    },
    "', DELAY, 1)\" onmouseout=\"UnTip()\">LSCC": {
      "insider_buys": 0,
      "insider_events": 5
    },
    "', DELAY, 1)\" onmouseout=\"UnTip()\">AVAV": {
      "insider_buys": 0,
      "insider_events": 1
    },
    "', DELAY, 1)\" onmouseout=\"UnTip()\">UUUU": {
      "insider_buys": 0,
      "insider_events": 2
    },
    "', DELAY, 1)\" onmouseout=\"UnTip()\">NPK": {
      "insider_buys": 0,
      "insider_events": 1
    },
    "', DELAY, 1)\" onmouseout=\"UnTip()\">FSBC": {
      "insider_buys": 0,
      "insider_events": 1
    },
    "', DELAY, 1)\" onmouseout=\"UnTip()\">AQST": {
      "insider_buys": 0,
      "insider_events": 7
    },
    "', DELAY, 1)\" onmouseout=\"UnTip()\">MCD": {
      "insider_buys": 0,
      "insider_events": 1
    },
    "', DELAY, 1)\" onmouseout=\"UnTip()\">JHG": {
      "insider_buys": 0,
      "insider_events": 1
    },
    "', DELAY, 1)\" onmouseout=\"UnTip()\">NXG": {
      "insider_buys": 2,
      "insider_events": 2
    },
    "', DELAY, 1)\" onmouseout=\"UnTip()\">FRD": {
      "insider_buys": 1,
      "insider_events": 1
    },
    "', DELAY, 1)\" onmouseout=\"UnTip()\">WRLD": {
      "insider_buys": 0,
      "insider_events": 1
    },
    "', DELAY, 1)\" onmouseout=\"UnTip()\">GRNT": {
      "insider_buys": 3,
      "insider_events": 3
    },
    "', DELAY, 1)\" onmouseout=\"UnTip()\">SCI": {
      "insider_buys": 0,
      "insider_events": 1
    },
    "', DELAY, 1)\" onmouseout=\"UnTip()\">FRAF": {
      "insider_buys": 1,
      "insider_events": 1
    },
    "', DELAY, 1)\" onmouseout=\"UnTip()\">SSP": {
      "insider_buys": 1,
      "insider_events": 1
    },
    "', DELAY, 1)\" onmouseout=\"UnTip()\">CNR": {
      "insider_buys": 0,
      "insider_events": 2
    },
    "', DELAY, 1)\" onmouseout=\"UnTip()\">ALG": {
      "insider_buys": 1,
      "insider_events": 1
    },
    "', DELAY, 1)\" onmouseout=\"UnTip()\">FDBC": {
      "insider_buys": 1,
      "insider_events": 1
    },
    "', DELAY, 1)\" onmouseout=\"UnTip()\">TPL": {
      "insider_buys": 1,
      "insider_events": 1
    },
    "', DELAY, 1)\" onmouseout=\"UnTip()\">RCG": {
      "insider_buys": 1,
      "insider_events": 1
    },
    "', DELAY, 1)\" onmouseout=\"UnTip()\">INDV": {
      "insider_buys": 2,
      "insider_events": 2
    },
    "', DELAY, 1)\" onmouseout=\"UnTip()\">BWFG": {
      "insider_buys": 1,
      "insider_events": 1
    },
    "', DELAY, 1)\" onmouseout=\"UnTip()\">AFL": {
      "insider_buys": 0,
      "insider_events": 1
    },
    "', DELAY, 1)\" onmouseout=\"UnTip()\">ENTX": {
      "insider_buys": 1,
      "insider_events": 1
    },
    "', DELAY, 1)\" onmouseout=\"UnTip()\">RMD": {
      "insider_buys": 0,
      "insider_events": 1
    },
    "', DELAY, 1)\" onmouseout=\"UnTip()\">CSTM": {
      "insider_buys": 3,
      "insider_events": 9
    },
    "', DELAY, 1)\" onmouseout=\"UnTip()\">SOLV": {
      "insider_buys": 1,
      "insider_events": 1
    },
    "', DELAY, 1)\" onmouseout=\"UnTip()\">FOUR": {
      "insider_buys": 1,
      "insider_events": 1
    },
    "', DELAY, 1)\" onmouseout=\"UnTip()\">GRMN": {
      "insider_buys": 0,
      "insider_events": 1
    },
    "', DELAY, 1)\" onmouseout=\"UnTip()\">SBC": {
      "insider_buys": 0,
      "insider_events": 1
    },
    "', DELAY, 1)\" onmouseout=\"UnTip()\">FOXX": {
      "insider_buys": 0,
      "insider_events": 1
    },
    "', DELAY, 1)\" onmouseout=\"UnTip()\">FPH": {
      "insider_buys": 0,
      "insider_events": 1
    },
    "', DELAY, 1)\" onmouseout=\"UnTip()\">MCS": {
      "insider_buys": 0,
      "insider_events": 1
    },
    "', DELAY, 1)\" onmouseout=\"UnTip()\">ABOS": {
      "insider_buys": 0,
      "insider_events": 1
    },
    "', DELAY, 1)\" onmouseout=\"UnTip()\">AM": {
      "insider_buys": 0,
      "insider_events": 2
    },
    "', DELAY, 1)\" onmouseout=\"UnTip()\">MNKD": {
      "insider_buys": 1,
      "insider_events": 1
    },
    "', DELAY, 1)\" onmouseout=\"UnTip()\">AR": {
      "insider_buys": 0,
      "insider_events": 2
    },
    "', DELAY, 1)\" onmouseout=\"UnTip()\">GCT": {
      "insider_buys": 0,
      "insider_events": 1
    },
    "', DELAY, 1)\" onmouseout=\"UnTip()\">NTRA": {
      "insider_buys": 0,
      "insider_events": 1
    },
    "', DELAY, 1)\" onmouseout=\"UnTip()\">FSLR": {
      "insider_buys": 0,
      "insider_events": 11
    },
    "', DELAY, 1)\" onmouseout=\"UnTip()\">ADMA": {
      "insider_buys": 0,
      "insider_events": 1
    },
    "', DELAY, 1)\" onmouseout=\"UnTip()\">ENOV": {
      "insider_buys": 1,
      "insider_events": 1
    },
    "', DELAY, 1)\" onmouseout=\"UnTip()\">NAMS": {
      "insider_buys": 0,
      "insider_events": 1
    },
    "', DELAY, 1)\" onmouseout=\"UnTip()\">FLEX": {
      "insider_buys": 0,
      "insider_events": 1
    },
    "', DELAY, 1)\" onmouseout=\"UnTip()\">ACEL": {
      "insider_buys": 1,
      "insider_events": 3
    },
    "', DELAY, 1)\" onmouseout=\"UnTip()\">OKLO": {
      "insider_buys": 0,
      "insider_events": 1
    },
    "', DELAY, 1)\" onmouseout=\"UnTip()\">ADPT": {
      "insider_buys": 0,
      "insider_events": 1
    },
    "', DELAY, 1)\" onmouseout=\"UnTip()\">TKO": {
      "insider_buys": 0,
      "insider_events": 1
    },
    "', DELAY, 1)\" onmouseout=\"UnTip()\">COLD": {
      "insider_buys": 0,
      "insider_events": 1
    },
    "', DELAY, 1)\" onmouseout=\"UnTip()\">THC": {
      "insider_buys": 0,
      "insider_events": 1
    },
    "', DELAY, 1)\" onmouseout=\"UnTip()\">CXDO": {
      "insider_buys": 0,
      "insider_events": 1
    },
    "', DELAY, 1)\" onmouseout=\"UnTip()\">SHC": {
      "insider_buys": 0,
      "insider_events": 2
    },
    "', DELAY, 1)\" onmouseout=\"UnTip()\">GO": {
      "insider_buys": 0,
      "insider_events": 3
    }
  },
  "macro_regime": {
    "vix": 24.93,
    "dgs10": 4.12,
    "dxy": 119.491,
    "macro_adj": -8,
    "macro_reasons": [
      "macro_vix_alto"
    ]
  },
  "top_opportunities": [
    {
      "ticker": "XLE",
      "ok": true,
      "currency": "USD",
      "exchange": "PCX",
      "regularMarketPrice": 56.665,
      "previousClose": null,
      "lastCloseSeries": 56.665000915527344,
      "chg_5d_pct": 0.85,
      "chg_20d_pct": 5.76,
      "ema20": 55.141,
      "ema50": 52.256,
      "sma200": 45.728,
      "overextension_200d_pct": 23.92,
      "rsi14": 65.91,
      "bb_upper": 57.315,
      "bb_lower": 53.623,
      "rel_volume": 0.5,
      "breakout_20": false,
      "intraday_15m_bias": "alcista",
      "score_tech": 96,
      "score": 70,
      "reasons": [
        "momento_5d_positivo",
        "tendencia_20d_fuerte",
        "price_above_ema20",
        "ema20_above_ema50",
        "rsi_constructivo",
        "intraday_15m_alcista",
        "macro_vix_alto",
        "bubble_critical",
        "devil_advocate_active"
      ],
      "score_social": null,
      "earnings_label": "No Data",
      "score_macro_adj": -8,
      "score_asymmetry": 0,
      "fundamental_inflection_score": 0,
      "catalyst_score": 0,
      "spinoff_score": 0,
      "insider_score": 0,
      "options_flow_score": 0,
      "options_cp_ratio": null,
      "insider_buys": 0,
      "convergence_count": 1,
      "state": "WATCH",
      "score_final": 70,
      "confidence_pct": 70,
      "bubble_level": "Crítico",
      "argumento_en_contra": "Divergencia bajista: precio sube con volumen débil",
      "decision_final": "HOLD"
    },
    {
      "ticker": "NVDA",
      "ok": true,
      "currency": "USD",
      "exchange": "NMS",
      "regularMarketPrice": 185.035,
      "previousClose": null,
      "lastCloseSeries": 185.03509521484375,
      "chg_5d_pct": 1.09,
      "chg_20d_pct": -1.86,
      "ema20": 184.479,
      "ema50": 184.945,
      "sma200": 176.903,
      "overextension_200d_pct": 4.6,
      "rsi14": 50.33,
      "bb_upper": 194.959,
      "bb_lower": 176.211,
      "rel_volume": 0.47,
      "breakout_20": false,
      "intraday_15m_bias": "bajista",
      "score_tech": 60,
      "score": 52,
      "reasons": [
        "momento_5d_positivo",
        "universo_prioritario",
        "price_above_ema20",
        "ema20_below_ema50",
        "rsi_constructivo",
        "intraday_15m_bajista",
        "macro_vix_alto",
        "social_bullish",
        "devil_advocate_active"
      ],
      "score_social": 50.0,
      "earnings_label": "No Data",
      "score_macro_adj": -8,
      "score_asymmetry": 0,
      "fundamental_inflection_score": 0,
      "catalyst_score": 0,
      "spinoff_score": 0,
      "insider_score": 0,
      "options_flow_score": 0,
      "options_cp_ratio": null,
      "insider_buys": 0,
      "convergence_count": 2,
      "state": "WATCH",
      "score_final": 52,
      "confidence_pct": 52,
      "bubble_level": "Bajo",
      "argumento_en_contra": "Divergencia bajista: precio sube con volumen débil",
      "decision_final": "AVOID"
    },
    {
      "ticker": "GLD",
      "ok": true,
      "currency": "USD",
      "exchange": "PCX",
      "regularMarketPrice": 474.63,
      "previousClose": null,
      "lastCloseSeries": 474.6300048828125,
      "chg_5d_pct": 0.6,
      "chg_20d_pct": 2.64,
      "ema20": 469.442,
      "ema50": 450.709,
      "sma200": 369.208,
      "overextension_200d_pct": 28.55,
      "rsi14": 54.62,
      "bb_upper": 490.363,
      "bb_lower": 449.781,
      "rel_volume": 0.43,
      "breakout_20": false,
      "intraday_15m_bias": "bajista",
      "score_tech": 76,
      "score": 50,
      "reasons": [
        "momento_5d_positivo",
        "tendencia_20d_positiva",
        "price_above_ema20",
        "ema20_above_ema50",
        "rsi_constructivo",
        "intraday_15m_bajista",
        "macro_vix_alto",
        "bubble_critical",
        "devil_advocate_active"
      ],
      "score_social": null,
      "earnings_label": "No Data",
      "score_macro_adj": -8,
      "score_asymmetry": 0,
      "fundamental_inflection_score": 0,
      "catalyst_score": 0,
      "spinoff_score": 0,
      "insider_score": 0,
      "options_flow_score": 0,
      "options_cp_ratio": null,
      "insider_buys": 0,
      "convergence_count": 1,
      "state": "WATCH",
      "score_final": 50,
      "confidence_pct": 50,
      "bubble_level": "Crítico",
      "argumento_en_contra": "Divergencia bajista: precio sube con volumen débil",
      "decision_final": "AVOID"
    },
    {
      "ticker": "AVGO",
      "ok": true,
      "currency": "USD",
      "exchange": "NMS",
      "regularMarketPrice": 339.505,
      "previousClose": null,
      "lastCloseSeries": 339.5050048828125,
      "chg_5d_pct": 6.92,
      "chg_20d_pct": -0.27,
      "ema20": 331.289,
      "ema50": 335.051,
      "sma200": 322.38,
      "overextension_200d_pct": 5.31,
      "rsi14": 55.07,
      "bb_upper": 347.322,
      "bb_lower": 312.924,
      "rel_volume": 0.39,
      "breakout_20": false,
      "intraday_15m_bias": "bajista",
      "score_tech": 66,
      "score": 44,
      "reasons": [
        "momento_5d_fuerte",
        "universo_prioritario",
        "price_above_ema20",
        "ema20_below_ema50",
        "rsi_constructivo",
        "intraday_15m_bajista",
        "macro_vix_alto",
        "earnings_calendar_signal",
        "devil_advocate_active"
      ],
      "score_social": null,
      "earnings_label": "Earnings Miss/Inline",
      "score_macro_adj": -8,
      "score_asymmetry": 0,
      "fundamental_inflection_score": 0,
      "catalyst_score": 0,
      "spinoff_score": 0,
      "insider_score": 0,
      "options_flow_score": 0,
      "options_cp_ratio": null,
      "insider_buys": 0,
      "convergence_count": 1,
      "state": "WATCH",
      "score_final": 44,
      "confidence_pct": 44,
      "bubble_level": "Medio",
      "argumento_en_contra": "Divergencia bajista: precio sube con volumen débil",
      "decision_final": "AVOID"
    },
    {
      "ticker": "XLF",
      "ok": true,
      "currency": "USD",
      "exchange": "PCX",
      "regularMarketPrice": 49.43,
      "previousClose": null,
      "lastCloseSeries": 49.43000030517578,
      "chg_5d_pct": -4.02,
      "chg_20d_pct": -7.69,
      "ema20": 51.411,
      "ema50": 52.471,
      "sma200": 52.835,
      "overextension_200d_pct": -6.44,
      "rsi14": 31.51,
      "bb_upper": 53.186,
      "bb_lower": 49.679,
      "rel_volume": 0.6,
      "breakout_20": false,
      "intraday_15m_bias": "bajista",
      "score_tech": 0,
      "score": 42,
      "reasons": [
        "momento_5d_debil",
        "tendencia_20d_debil",
        "price_below_ema20",
        "ema20_below_ema50",
        "rsi_debil",
        "bollinger_breakdown",
        "intraday_15m_bajista",
        "macro_vix_alto"
      ],
      "score_social": null,
      "earnings_label": "No Data",
      "score_macro_adj": -8,
      "score_asymmetry": 0,
      "fundamental_inflection_score": 0,
      "catalyst_score": 0,
      "spinoff_score": 0,
      "insider_score": 0,
      "options_flow_score": 0,
      "options_cp_ratio": null,
      "insider_buys": 0,
      "convergence_count": 0,
      "state": "WATCH",
      "score_final": 42,
      "confidence_pct": 42,
      "bubble_level": "Bajo",
      "argumento_en_contra": "Sin objeción crítica detectada",
      "decision_final": "AVOID"
    }
  ]
}